[
  {
    "id": 1296504,
    "title": "Deep linking",
    "section_id": 157787,
    "template_id": 1,
    "type_id": 4,
    "priority_id": 6,
    "milestone_id": null,
    "refs": null,
    "created_by": 181,
    "created_on": 1580852513,
    "updated_by": 257,
    "updated_on": 1597983438,
    "estimate": null,
    "estimate_forecast": "18s",
    "suite_id": 22095,
    "display_order": 1,
    "custom_is_automated": true,
    "custom_automation_id": null,
    "custom_preconds": "Given:  User has opened the website",
    "custom_steps": "When the user Deep links to \"The Vault\" Page",
    "custom_expected": "Then the user is redirected to the \"The Vault\" page",
    "custom_steps_separated": null,
    "custom_comment": null,
    "custom_automation_id_temp": null
  },
  {
    "id": 1296505,
    "title": "Logo",
    "section_id": 157787,
    "template_id": 1,
    "type_id": 4,
    "priority_id": 6,
    "milestone_id": null,
    "refs": null,
    "created_by": 181,
    "created_on": 1580852513,
    "updated_by": 257,
    "updated_on": 1597983438,
    "estimate": null,
    "estimate_forecast": "19s",
    "suite_id": 22095,
    "display_order": 2,
    "custom_is_automated": true,
    "custom_automation_id": null,
    "custom_preconds": "Given the user is on the \"The Vault\" page",
    "custom_steps": "When the user lands on \"The Vault\" page",
    "custom_expected": "Then the user must see the Logos on the \"The Vault\" page",
    "custom_steps_separated": null,
    "custom_comment": null,
    "custom_automation_id_temp": null
  },
  {
    "id": 1296506,
    "title": "Web Elements",
    "section_id": 157787,
    "template_id": 1,
    "type_id": 4,
    "priority_id": 6,
    "milestone_id": null,
    "refs": null,
    "created_by": 181,
    "created_on": 1580852513,
    "updated_by": 257,
    "updated_on": 1597983436,
    "estimate": null,
    "estimate_forecast": "23s",
    "suite_id": 22095,
    "display_order": 3,
    "custom_is_automated": true,
    "custom_automation_id": null,
    "custom_preconds": "Given the user is on the \"The Vault\"page",
    "custom_steps": "When the user lands on \"The Vault\" page",
    "custom_expected": "Then the user must see page web elements(Selected Picks, games) on the \"The Vault\" page",
    "custom_steps_separated": null,
    "custom_comment": null,
    "custom_automation_id_temp": null
  },
  {
    "id": 1296507,
    "title": "Select a player",
    "section_id": 157787,
    "template_id": 1,
    "type_id": 4,
    "priority_id": 6,
    "milestone_id": null,
    "refs": null,
    "created_by": 181,
    "created_on": 1580852513,
    "updated_by": 257,
    "updated_on": 1597983438,
    "estimate": null,
    "estimate_forecast": "26s",
    "suite_id": 22095,
    "display_order": 4,
    "custom_is_automated": true,
    "custom_automation_id": null,
    "custom_preconds": "Given the user is on the \"The Vault\" page",
    "custom_steps": "When the user lands on \"The Vault\" page And selects a player in Home Runs tab",
    "custom_expected": "Then the player must be selected in the respective stats field",
    "custom_steps_separated": null,
    "custom_comment": null,
    "custom_automation_id_temp": null
  },
  {
    "id": 1296508,
    "title": "Form Web Elements",
    "section_id": 157787,
    "template_id": 1,
    "type_id": 4,
    "priority_id": 6,
    "milestone_id": null,
    "refs": null,
    "created_by": 181,
    "created_on": 1580852513,
    "updated_by": 257,
    "updated_on": 1597983437,
    "estimate": null,
    "estimate_forecast": "29s",
    "suite_id": 22095,
    "display_order": 5,
    "custom_is_automated": true,
    "custom_automation_id": null,
    "custom_preconds": "Given the user is on the \"The Vault\" page",
    "custom_steps": "When the user lands on \"The Vault\" page And selects a player in Home Runs tab",
    "custom_expected": "Then the user must see Form web elements(Email, Birth date, State, Zip, submit button)",
    "custom_steps_separated": null,
    "custom_comment": null,
    "custom_automation_id_temp": null
  },
  {
    "id": 1296509,
    "title": "Submit form",
    "section_id": 157787,
    "template_id": 1,
    "type_id": 4,
    "priority_id": 6,
    "milestone_id": null,
    "refs": null,
    "created_by": 181,
    "created_on": 1580852513,
    "updated_by": 257,
    "updated_on": 1597983437,
    "estimate": null,
    "estimate_forecast": "39s",
    "suite_id": 22095,
    "display_order": 6,
    "custom_is_automated": true,
    "custom_automation_id": null,
    "custom_preconds": "Given the user is on the \"The Vault\" page",
    "custom_steps": "When the user lands on \"The Vault\" page And selects a player in Home Runs tab and submits the form",
    "custom_expected": "Then the user can see Success message",
    "custom_steps_separated": null,
    "custom_comment": null,
    "custom_automation_id_temp": null
  },
  {
    "id": 1297123,
    "title": "Ads",
    "section_id": 157787,
    "template_id": 1,
    "type_id": 4,
    "priority_id": 6,
    "milestone_id": null,
    "refs": null,
    "created_by": 181,
    "created_on": 1581348536,
    "updated_by": 257,
    "updated_on": 1597983439,
    "estimate": null,
    "estimate_forecast": "19s",
    "suite_id": 22095,
    "display_order": 7,
    "custom_is_automated": true,
    "custom_automation_id": null,
    "custom_preconds": "Given: User has opened the website",
    "custom_steps": "When the user Deep links to \"The Vault\" Page",
    "custom_expected": "Then the user must see ads",
    "custom_steps_separated": null,
    "custom_comment": null,
    "custom_automation_id_temp": null
  },
  {
    "id": 1297125,
    "title": "Rules in footer",
    "section_id": 157787,
    "template_id": 1,
    "type_id": 4,
    "priority_id": 6,
    "milestone_id": null,
    "refs": null,
    "created_by": 181,
    "created_on": 1581348661,
    "updated_by": 257,
    "updated_on": 1597983439,
    "estimate": null,
    "estimate_forecast": "19s",
    "suite_id": 22095,
    "display_order": 8,
    "custom_is_automated": true,
    "custom_automation_id": null,
    "custom_preconds": "Given: User has opened the website",
    "custom_steps": "When the user Deep links to \"The Vault\" Page",
    "custom_expected": "Then the user must see rules in the footer",
    "custom_steps_separated": null,
    "custom_comment": null,
    "custom_automation_id_temp": null
  },
  {
    "id": 1297300,
    "title": "Coppa",
    "section_id": 157787,
    "template_id": 1,
    "type_id": 4,
    "priority_id": 6,
    "milestone_id": null,
    "refs": null,
    "created_by": 181,
    "created_on": 1581451018,
    "updated_by": 257,
    "updated_on": 1584028227,
    "estimate": null,
    "estimate_forecast": "12s",
    "suite_id": 22095,
    "display_order": 9,
    "custom_is_automated": true,
    "custom_automation_id": null,
    "custom_preconds": "Given: User is on the \"The Vault\" page",
    "custom_steps": "When the user selects a player and submits form with birthyear 2020",
    "custom_expected": "Then the user must see form ineligible text",
    "custom_steps_separated": null,
    "custom_comment": null,
    "custom_automation_id_temp": null
  }
]