[
  {
    "id": 1248448,
    "title": "Preview - One Line",
    "section_id": 151708,
    "template_id": 1,
    "type_id": 4,
    "priority_id": 6,
    "milestone_id": null,
    "refs": null,
    "created_by": 171,
    "created_on": 1565199932,
    "updated_by": 188,
    "updated_on": 1565218077,
    "estimate": null,
    "estimate_forecast": null,
    "suite_id": 20832,
    "display_order": 1,
    "custom_preconds": "GIVEN\r\nThere is a game in the Pregame state AND set to one line",
    "custom_steps": "WHEN\r\nThe user navigates to Scoreboard List View",
    "custom_expected": "THEN\r\nthe following elements should be displayed:\r\nhttps://zpl.io/VQQjp6x\r\n - Game label text is displayed in One Line\r\n - Team Logos\r\n - Team Code\r\n - Team Records\r\n - First Pitch Gametime (local time zone support)\r\n - Probable Pitchers and Stats",
    "custom_steps_separated": null
  },
  {
    "id": 1248449,
    "title": "Preview - Two Lines",
    "section_id": 151708,
    "template_id": 1,
    "type_id": 4,
    "priority_id": 6,
    "milestone_id": null,
    "refs": null,
    "created_by": 171,
    "created_on": 1565199932,
    "updated_by": 188,
    "updated_on": 1565218089,
    "estimate": null,
    "estimate_forecast": null,
    "suite_id": 20832,
    "display_order": 2,
    "custom_preconds": "GIVEN\r\nThere is a game in the Pregame state AND set to two lines",
    "custom_steps": "WHEN\r\nThe user navigates to Scoreboard List View",
    "custom_expected": "THEN\r\nthe following elements should be displayed:\r\nhttps://zpl.io/VQQjp6x\r\n - Game label text is displayed in Two Lines\r\n - Team Logos\r\n - Team Code\r\n - Team Records\r\n - First Pitch Gametime (local time zone support)\r\n - Probable Pitchers and Stats",
    "custom_steps_separated": null
  },
  {
    "id": 1248450,
    "title": "Preview - Delayed Start",
    "section_id": 151708,
    "template_id": 1,
    "type_id": 4,
    "priority_id": 6,
    "milestone_id": null,
    "refs": null,
    "created_by": 171,
    "created_on": 1565199932,
    "updated_by": 188,
    "updated_on": 1565218098,
    "estimate": null,
    "estimate_forecast": null,
    "suite_id": 20832,
    "display_order": 3,
    "custom_preconds": "GIVEN\r\nThere is a game in the Pregame state AND the game has a Delayed Start",
    "custom_steps": "WHEN\r\nThe user navigates to Scoreboard List View",
    "custom_expected": "THEN\r\nthe following elements should be displayed:\r\nhttps://zpl.io/VQQjp6x\r\n - Delayed text displays\r\n - Team Logos\r\n - Team Code\r\n - Team Records\r\n - First Pitch Gametime (local time zone support)\r\n - Probable Pitchers and Stats\r\n\r\n",
    "custom_steps_separated": null
  },
  {
    "id": 1248451,
    "title": "Preview - Delayed Start Ceremony",
    "section_id": 151708,
    "template_id": 1,
    "type_id": 4,
    "priority_id": 6,
    "milestone_id": null,
    "refs": null,
    "created_by": 171,
    "created_on": 1565199932,
    "updated_by": 188,
    "updated_on": 1565218114,
    "estimate": null,
    "estimate_forecast": null,
    "suite_id": 20832,
    "display_order": 4,
    "custom_preconds": "GIVEN\r\nThere is a game in the Pregame state AND the game is a Delayed Start Ceremony",
    "custom_steps": "WHEN\r\nThe user navigates to Scoreboard List View",
    "custom_expected": "THEN\r\nthe following elements should be displayed:\r\nhttps://zpl.io/VQQjp6x\r\n - Ceremony text displays\r\n - Team Logos\r\n - Team Code\r\n - Team Records\r\n - First Pitch Gametime (local time zone support)\r\n - Probable Pitchers and Stats\r\n\r\n\r\n",
    "custom_steps_separated": null
  },
  {
    "id": 1248452,
    "title": "Preview - Double Header Game 2 (Single Ticket)",
    "section_id": 151708,
    "template_id": 1,
    "type_id": 4,
    "priority_id": 6,
    "milestone_id": null,
    "refs": null,
    "created_by": 171,
    "created_on": 1565199932,
    "updated_by": 188,
    "updated_on": 1565218127,
    "estimate": null,
    "estimate_forecast": null,
    "suite_id": 20832,
    "display_order": 5,
    "custom_preconds": "GIVEN\r\nThere is a game in the Pregame state AND the game is a Double Header",
    "custom_steps": "WHEN\r\nThe user navigates to Scoreboard List View",
    "custom_expected": "THEN\r\nthe following elements should be displayed:\r\nhttps://zpl.io/VQQjp6x\r\n - Game info for two games are displayed\r\n - Team Logos\r\n - Team Code\r\n - Team Records\r\n - First Pitch Gametime (local time zone support)\r\n - Probable Pitchers and Stats",
    "custom_steps_separated": null
  },
  {
    "id": 1248453,
    "title": "Preview - No Start Time",
    "section_id": 151708,
    "template_id": 1,
    "type_id": 4,
    "priority_id": 6,
    "milestone_id": null,
    "refs": null,
    "created_by": 171,
    "created_on": 1565199932,
    "updated_by": 188,
    "updated_on": 1565218139,
    "estimate": null,
    "estimate_forecast": null,
    "suite_id": 20832,
    "display_order": 6,
    "custom_preconds": "GIVEN\r\nThere is a game in the Pregame state AND there is no start time",
    "custom_steps": "WHEN\r\nThe user navigates to Scoreboard List View",
    "custom_expected": "THEN\r\nthe following elements should be displayed:\r\nhttps://zpl.io/VQQjp6x\r\n - TBD text is displayed\r\n - Team Logos\r\n - Team Code\r\n - Team Records\r\n - First Pitch Gametime (local time zone support)\r\n - Probable Pitchers and Stats",
    "custom_steps_separated": null
  },
  {
    "id": 1248454,
    "title": "Preview - No Records",
    "section_id": 151708,
    "template_id": 1,
    "type_id": 4,
    "priority_id": 6,
    "milestone_id": null,
    "refs": null,
    "created_by": 171,
    "created_on": 1565199932,
    "updated_by": 188,
    "updated_on": 1565218151,
    "estimate": null,
    "estimate_forecast": null,
    "suite_id": 20832,
    "display_order": 7,
    "custom_preconds": "GIVEN\r\nThere is a game in the Pregame state AND there are no records",
    "custom_steps": "WHEN\r\nThe user navigates to Scoreboard List View",
    "custom_expected": "THEN\r\nthe following elements should be displayed:\r\nhttps://zpl.io/VQQjp6x\r\n- Team records are not displayed\r\n- Team Logos\r\n- Team Code\r\n- Team Records\r\n- First Pitch Gametime (local time zone support)\r\n- Probable Pitchers and Stats\r\n",
    "custom_steps_separated": null
  },
  {
    "id": 1248455,
    "title": "Live - One Line",
    "section_id": 151709,
    "template_id": 1,
    "type_id": 4,
    "priority_id": 6,
    "milestone_id": null,
    "refs": null,
    "created_by": 171,
    "created_on": 1565199932,
    "updated_by": 188,
    "updated_on": 1565216511,
    "estimate": null,
    "estimate_forecast": null,
    "suite_id": 20832,
    "display_order": 1,
    "custom_preconds": "GIVEN\r\nThere is a game in the Live state",
    "custom_steps": "WHEN\r\nThe user navigates to Scoreboard List View",
    "custom_expected": "THEN\r\nthe following elements should be displayed:\r\nhttps://zpl.io/VQQjp6x\r\n - Game label is displayed in One Line\r\n - Linescore\r\n - Scores\r\n - Bases\r\n - Pitch Count\r\n - Outs\r\n - Inning\r\n - Pitcher/Batter Matchup",
    "custom_steps_separated": null
  },
  {
    "id": 1248456,
    "title": "Live - Warmup",
    "section_id": 151709,
    "template_id": 1,
    "type_id": 4,
    "priority_id": 6,
    "milestone_id": null,
    "refs": null,
    "created_by": 171,
    "created_on": 1565199932,
    "updated_by": 188,
    "updated_on": 1565216549,
    "estimate": null,
    "estimate_forecast": null,
    "suite_id": 20832,
    "display_order": 2,
    "custom_preconds": "GIVEN\r\nThere is a game in the Live state AND the game is in the Warmup stage",
    "custom_steps": "WHEN\r\nThe user navigates to Scoreboard List View",
    "custom_expected": "THEN\r\nthe following elements should be displayed:\r\nhttps://zpl.io/VQQjp6x\r\n - Warmup text is displayed\r\n - Linescore\r\n - Scores\r\n - Bases\r\n - Pitch Count\r\n - Outs\r\n - Inning\r\n - Pitcher/Batter Matchup",
    "custom_steps_separated": null
  },
  {
    "id": 1248457,
    "title": "Live - In Game Delay",
    "section_id": 151709,
    "template_id": 1,
    "type_id": 4,
    "priority_id": 6,
    "milestone_id": null,
    "refs": null,
    "created_by": 171,
    "created_on": 1565199932,
    "updated_by": 188,
    "updated_on": 1565216560,
    "estimate": null,
    "estimate_forecast": null,
    "suite_id": 20832,
    "display_order": 3,
    "custom_preconds": "GIVEN\r\nThere is a game in the Live state AND the game has an In Game Delay",
    "custom_steps": "WHEN\r\nThe user navigates to Scoreboard List View",
    "custom_expected": "THEN\r\nthe following elements should be displayed:\r\nhttps://zpl.io/VQQjp6x\r\n - Delayed text displays\r\n - Linescore\r\n - Scores\r\n - Bases\r\n - Pitch Count\r\n - Outs\r\n - Inning\r\n - Pitcher/Batter Matchup",
    "custom_steps_separated": null
  },
  {
    "id": 1248458,
    "title": "Live - Manager Challenge",
    "section_id": 151709,
    "template_id": 1,
    "type_id": 4,
    "priority_id": 6,
    "milestone_id": null,
    "refs": null,
    "created_by": 171,
    "created_on": 1565199932,
    "updated_by": 188,
    "updated_on": 1565216573,
    "estimate": null,
    "estimate_forecast": null,
    "suite_id": 20832,
    "display_order": 4,
    "custom_preconds": "GIVEN\r\nThere is a game in the Live state AND the game has a Manager Challenge",
    "custom_steps": "WHEN\r\nThe user navigates to Scoreboard List View",
    "custom_expected": "THEN\r\nthe following elements should be displayed:\r\nhttps://zpl.io/VQQjp6x\r\n - <team code> Chal text displays\r\n - Linescore\r\n - Scores\r\n - Bases\r\n - Pitch Count\r\n - Outs\r\n - Inning\r\n - Pitcher/Batter Matchup",
    "custom_steps_separated": null
  },
  {
    "id": 1248459,
    "title": "Live - No Hitter",
    "section_id": 151709,
    "template_id": 1,
    "type_id": 4,
    "priority_id": 6,
    "milestone_id": null,
    "refs": null,
    "created_by": 171,
    "created_on": 1565199932,
    "updated_by": 188,
    "updated_on": 1565216591,
    "estimate": null,
    "estimate_forecast": null,
    "suite_id": 20832,
    "display_order": 5,
    "custom_preconds": "GIVEN\r\nThere is a game in the Live state AND the game has a No Hitter",
    "custom_steps": "WHEN\r\nThe user navigates to Scoreboard List View",
    "custom_expected": "THEN\r\nthe following elements should be displayed:\r\nhttps://zpl.io/VQQjp6x\r\n - No-Hitter text displays in RED\r\n - Linescore\r\n - Scores\r\n - Bases\r\n - Pitch Count\r\n - Outs\r\n - Inning\r\n - Pitcher/Batter Matchup",
    "custom_steps_separated": null
  },
  {
    "id": 1248460,
    "title": "Live - Perfect Game",
    "section_id": 151709,
    "template_id": 1,
    "type_id": 4,
    "priority_id": 6,
    "milestone_id": null,
    "refs": null,
    "created_by": 171,
    "created_on": 1565199932,
    "updated_by": 188,
    "updated_on": 1565216605,
    "estimate": null,
    "estimate_forecast": null,
    "suite_id": 20832,
    "display_order": 6,
    "custom_preconds": "GIVEN\r\nThere is a game in the Live state AND the game is a Perfect Game",
    "custom_steps": "WHEN\r\nThe user navigates to Scoreboard List View",
    "custom_expected": "THEN\r\nthe following elements should be displayed:\r\nhttps://zpl.io/VQQjp6x\r\n - Perfect Game text displays in RED\r\n - Linescore\r\n - Scores\r\n - Bases\r\n - Pitch Count\r\n - Outs\r\n - Inning\r\n - Pitcher/Batter Matchup",
    "custom_steps_separated": null
  },
  {
    "id": 1248461,
    "title": "Live - Delay Ceremony",
    "section_id": 151709,
    "template_id": 1,
    "type_id": 4,
    "priority_id": 6,
    "milestone_id": null,
    "refs": null,
    "created_by": 171,
    "created_on": 1565199932,
    "updated_by": 188,
    "updated_on": 1565216615,
    "estimate": null,
    "estimate_forecast": null,
    "suite_id": 20832,
    "display_order": 7,
    "custom_preconds": "GIVEN\r\nThere is a game in the Live state AND the game is a Delay Ceremony",
    "custom_steps": "WHEN\r\nThe user navigates to Scoreboard List View",
    "custom_expected": "THEN\r\nthe following elements should be displayed:\r\nhttps://zpl.io/VQQjp6x\r\n - Ceremony text displays\r\n - Linescore\r\n - Scores\r\n - Bases\r\n - Pitch Count\r\n - Outs\r\n - Inning\r\n - Pitcher/Batter Matchup",
    "custom_steps_separated": null
  },
  {
    "id": 1248462,
    "title": "Final",
    "section_id": 151710,
    "template_id": 1,
    "type_id": 4,
    "priority_id": 6,
    "milestone_id": null,
    "refs": null,
    "created_by": 171,
    "created_on": 1565199932,
    "updated_by": 188,
    "updated_on": 1565216628,
    "estimate": null,
    "estimate_forecast": null,
    "suite_id": 20832,
    "display_order": 1,
    "custom_preconds": "GIVEN\r\nThere is a game in the Final state",
    "custom_steps": "WHEN\r\nThe user navigates to Scoreboard List View",
    "custom_expected": "THEN\r\nthe following elements should be displayed:\r\nhttps://zpl.io/VQQjp6x\r\n - Final text displays\r\n - Winning/Losing/Save Pitcher\r\n - Final Score\r\n - Updated Team Records\r\n - Complete linescore for all innings played",
    "custom_steps_separated": null
  },
  {
    "id": 1248463,
    "title": "Final - 12 Innings",
    "section_id": 151710,
    "template_id": 1,
    "type_id": 4,
    "priority_id": 6,
    "milestone_id": null,
    "refs": null,
    "created_by": 171,
    "created_on": 1565199932,
    "updated_by": 188,
    "updated_on": 1565216636,
    "estimate": null,
    "estimate_forecast": null,
    "suite_id": 20832,
    "display_order": 2,
    "custom_preconds": "GIVEN\r\nThere is a game in the Final state AND the game lasts 12 innings",
    "custom_steps": "WHEN\r\nThe user navigates to Scoreboard List View",
    "custom_expected": "THEN\r\nthe following elements should be displayed:\r\nhttps://zpl.io/VQQjp6x\r\n - Final text displays w total number of innings (Final/12)\r\n - Winning/Losing/Save Pitcher\r\n - Final Score\r\n - Updated Team Records\r\n - Complete linescore for all innings played",
    "custom_steps_separated": null
  },
  {
    "id": 1248464,
    "title": "Final - 7 Innings, Completed Early",
    "section_id": 151710,
    "template_id": 1,
    "type_id": 4,
    "priority_id": 6,
    "milestone_id": null,
    "refs": null,
    "created_by": 171,
    "created_on": 1565199932,
    "updated_by": 188,
    "updated_on": 1565216660,
    "estimate": null,
    "estimate_forecast": null,
    "suite_id": 20832,
    "display_order": 3,
    "custom_preconds": "GIVEN\r\nThere is a game in the Final state AND the game is completed early at 7 innings",
    "custom_steps": "WHEN\r\nThe user navigates to Scoreboard List View",
    "custom_expected": "THEN\r\nthe following elements should be displayed:\r\nhttps://zpl.io/VQQjp6x\r\n - Final text displays w total number of innings (Final/7)\r\n - Winning/Losing/Save Pitcher\r\n - Final Score\r\n - Updated Team Records\r\n - Complete linescore for all innings played",
    "custom_steps_separated": null
  },
  {
    "id": 1248465,
    "title": "Final - No Hitter",
    "section_id": 151710,
    "template_id": 1,
    "type_id": 4,
    "priority_id": 6,
    "milestone_id": null,
    "refs": null,
    "created_by": 171,
    "created_on": 1565199932,
    "updated_by": 188,
    "updated_on": 1565216679,
    "estimate": null,
    "estimate_forecast": null,
    "suite_id": 20832,
    "display_order": 4,
    "custom_preconds": "GIVEN\r\nThere is a game in the Final state AND the game was a No Hitter",
    "custom_steps": "WHEN\r\nThe user navigates to Scoreboard List View",
    "custom_expected": "THEN\r\nthe following elements should be displayed:\r\nhttps://zpl.io/VQQjp6x\r\n - No-Hitter text displays in RED\r\n - Winning/Losing/Save Pitcher\r\n - Final Score\r\n - Updated Team Records\r\n - Complete linescore for all innings played",
    "custom_steps_separated": null
  },
  {
    "id": 1248466,
    "title": "Final - Perfect Game",
    "section_id": 151710,
    "template_id": 1,
    "type_id": 4,
    "priority_id": 6,
    "milestone_id": null,
    "refs": null,
    "created_by": 171,
    "created_on": 1565199932,
    "updated_by": 188,
    "updated_on": 1565216685,
    "estimate": null,
    "estimate_forecast": null,
    "suite_id": 20832,
    "display_order": 5,
    "custom_preconds": "GIVEN\r\nThere is a game in the Final state AND the game was a Perfect Game",
    "custom_steps": "WHEN\r\nThe user navigates to Scoreboard List View",
    "custom_expected": "THEN\r\nthe following elements should be displayed:\r\nhttps://zpl.io/VQQjp6x\r\n - Perfect game text displays in RED\r\n - Winning/Losing/Save Pitcher\r\n - Final Score\r\n - Updated Team Records\r\n - Complete linescore for all innings played",
    "custom_steps_separated": null
  },
  {
    "id": 1248467,
    "title": "Misc - Postponed",
    "section_id": 151711,
    "template_id": 1,
    "type_id": 4,
    "priority_id": 6,
    "milestone_id": null,
    "refs": null,
    "created_by": 171,
    "created_on": 1565199932,
    "updated_by": 188,
    "updated_on": 1565216693,
    "estimate": null,
    "estimate_forecast": null,
    "suite_id": 20832,
    "display_order": 1,
    "custom_preconds": "GIVEN\r\nThere is a game in the Postponed state",
    "custom_steps": "WHEN\r\nThe user navigates to Scoreboard List View",
    "custom_expected": "THEN\r\nThe following elements should be displayed:\r\nhttps://zpl.io/VQQjp6x\r\n - Postponed text displays",
    "custom_steps_separated": null
  },
  {
    "id": 1248468,
    "title": "Misc - Suspended Day of Game",
    "section_id": 151711,
    "template_id": 1,
    "type_id": 4,
    "priority_id": 6,
    "milestone_id": null,
    "refs": null,
    "created_by": 171,
    "created_on": 1565199932,
    "updated_by": 188,
    "updated_on": 1565216703,
    "estimate": null,
    "estimate_forecast": null,
    "suite_id": 20832,
    "display_order": 2,
    "custom_preconds": "Need precondition setup process",
    "custom_steps": "WHEN\r\nThe user navigates to Scoreboard List View",
    "custom_expected": "THEN\r\nThe following elements should be displayed:\r\nhttps://zpl.io/VQQjp6x\r\n - Susp text displays",
    "custom_steps_separated": null
  },
  {
    "id": 1248469,
    "title": "Misc - Suspended Resume Game(Need clarity on this state - what does it mean)",
    "section_id": 151711,
    "template_id": 1,
    "type_id": 4,
    "priority_id": 6,
    "milestone_id": null,
    "refs": null,
    "created_by": 171,
    "created_on": 1565199932,
    "updated_by": 188,
    "updated_on": 1565216758,
    "estimate": null,
    "estimate_forecast": null,
    "suite_id": 20832,
    "display_order": 3,
    "custom_preconds": "Need precondition setup process",
    "custom_steps": "WHEN\r\nThe user navigates to Scoreboard List View",
    "custom_expected": "THEN\r\nThe following elements should be displayed:\r\nhttps://zpl.io/VQQjp6x\r\n - Susp text displays",
    "custom_steps_separated": null
  },
  {
    "id": 1248470,
    "title": "Misc - Canceled",
    "section_id": 151711,
    "template_id": 1,
    "type_id": 4,
    "priority_id": 6,
    "milestone_id": null,
    "refs": null,
    "created_by": 171,
    "created_on": 1565199932,
    "updated_by": 188,
    "updated_on": 1565216768,
    "estimate": null,
    "estimate_forecast": null,
    "suite_id": 20832,
    "display_order": 4,
    "custom_preconds": "GIVEN\r\nThere is a game in the Canceled state",
    "custom_steps": "WHEN\r\nThe user navigates to Scoreboard List View",
    "custom_expected": "THEN\r\nThe following elements should be displayed:\r\nhttps://zpl.io/VQQjp6x\r\n - Cancelled text displays",
    "custom_steps_separated": null
  },
  {
    "id": 1248471,
    "title": "Misc - Forfeit",
    "section_id": 151711,
    "template_id": 1,
    "type_id": 4,
    "priority_id": 6,
    "milestone_id": null,
    "refs": null,
    "created_by": 171,
    "created_on": 1565199932,
    "updated_by": 188,
    "updated_on": 1565216799,
    "estimate": null,
    "estimate_forecast": null,
    "suite_id": 20832,
    "display_order": 5,
    "custom_preconds": "GIVEN\r\nThere is a game that has been Forfeited",
    "custom_steps": "WHEN\r\nThe user navigates to Scoreboard List View",
    "custom_expected": "THEN\r\nThe following elements should be displayed:\r\nhttps://zpl.io/VQQjp6x\r\n - Forfiet text displays",
    "custom_steps_separated": null
  },
  {
    "id": 1248472,
    "title": "Misc - Favorite Team Designation\n(What happens here)",
    "section_id": 151711,
    "template_id": 1,
    "type_id": 4,
    "priority_id": 6,
    "milestone_id": null,
    "refs": null,
    "created_by": 171,
    "created_on": 1565199932,
    "updated_by": 171,
    "updated_on": 1565200112,
    "estimate": null,
    "estimate_forecast": null,
    "suite_id": 20832,
    "display_order": 6,
    "custom_preconds": null,
    "custom_steps": "WHEN\nThe user navigates to Scoreboard List View",
    "custom_expected": null,
    "custom_steps_separated": null
  },
  {
    "id": 1248473,
    "title": "Spring Training - Series Name One Line",
    "section_id": 151712,
    "template_id": 1,
    "type_id": 4,
    "priority_id": 6,
    "milestone_id": null,
    "refs": null,
    "created_by": 171,
    "created_on": 1565199932,
    "updated_by": 188,
    "updated_on": 1565216818,
    "estimate": null,
    "estimate_forecast": null,
    "suite_id": 20832,
    "display_order": 1,
    "custom_preconds": "GIVEN\r\nThere is a Spring Training Game is Live",
    "custom_steps": "WHEN\r\nThe user navigates to Scoreboard List View",
    "custom_expected": "THEN\r\nThe Series Name should appear in One Line\r\nhttps://zpl.io/VQQjp6x",
    "custom_steps_separated": null
  },
  {
    "id": 1248474,
    "title": "Spring Training - Preview(How is this Preview different for Spring Training)",
    "section_id": 151712,
    "template_id": 1,
    "type_id": 4,
    "priority_id": 6,
    "milestone_id": null,
    "refs": null,
    "created_by": 171,
    "created_on": 1565199932,
    "updated_by": 188,
    "updated_on": 1565212903,
    "estimate": null,
    "estimate_forecast": null,
    "suite_id": 20832,
    "display_order": 2,
    "custom_preconds": "GIVEN\r\nThere is a Spring Training game AND the game is in the Preview state",
    "custom_steps": "WHEN\r\nThe user navigates to Scoreboard List View",
    "custom_expected": "Need expected results",
    "custom_steps_separated": null
  },
  {
    "id": 1248475,
    "title": "Spring Training - Rain Delay(How is this different from Live In Game Delay)",
    "section_id": 151712,
    "template_id": 1,
    "type_id": 4,
    "priority_id": 6,
    "milestone_id": null,
    "refs": null,
    "created_by": 171,
    "created_on": 1565199932,
    "updated_by": 188,
    "updated_on": 1565216841,
    "estimate": null,
    "estimate_forecast": null,
    "suite_id": 20832,
    "display_order": 3,
    "custom_preconds": "GIVEN\r\nThere is a Spring Training game AND the game is Delayed",
    "custom_steps": "WHEN\r\nThe user navigates to Scoreboard List View",
    "custom_expected": "THEN\r\nThe following elements should be displayed:\r\nhttps://zpl.io/VQQjp6x\r\n - Delayed text displays",
    "custom_steps_separated": null
  },
  {
    "id": 1248476,
    "title": "Post Season - Preview - Game Info, Broadcast",
    "section_id": 151712,
    "template_id": 1,
    "type_id": 4,
    "priority_id": 6,
    "milestone_id": null,
    "refs": null,
    "created_by": 171,
    "created_on": 1565199932,
    "updated_by": 188,
    "updated_on": 1565216853,
    "estimate": null,
    "estimate_forecast": null,
    "suite_id": 20832,
    "display_order": 4,
    "custom_preconds": "GIVEN\r\nThere is a Post Season game that is in the Preview state AND set to display as one line",
    "custom_steps": "WHEN\r\nThe user navigates to Scoreboard List View",
    "custom_expected": "THEN\r\nThe following elements should be displayed:\r\nhttps://zpl.io/VQQjp6x\r\n - Game Info\r\n - Broadcast Logo",
    "custom_steps_separated": null
  },
  {
    "id": 1248477,
    "title": "Post Season - Preview - Two Lines, Delayed State",
    "section_id": 151712,
    "template_id": 1,
    "type_id": 4,
    "priority_id": 6,
    "milestone_id": null,
    "refs": null,
    "created_by": 171,
    "created_on": 1565199932,
    "updated_by": 188,
    "updated_on": 1565216876,
    "estimate": null,
    "estimate_forecast": null,
    "suite_id": 20832,
    "display_order": 5,
    "custom_preconds": "GIVEN\r\nThere is a Post Season game that is in the Preview and Delayed states AND set to display as two lines",
    "custom_steps": "WHEN\r\nThe user navigates to Scoreboard List View",
    "custom_expected": "THEN\r\nThe following elements should be displayed:\r\nhttps://zpl.io/VQQjp6x\r\n - Two Lines: Series Name, Game Info\r\n - Delayed State",
    "custom_steps_separated": null
  },
  {
    "id": 1248478,
    "title": "Post Season - Live: Two Lines, with Perfect Game",
    "section_id": 151712,
    "template_id": 1,
    "type_id": 4,
    "priority_id": 6,
    "milestone_id": null,
    "refs": null,
    "created_by": 171,
    "created_on": 1565199932,
    "updated_by": 188,
    "updated_on": 1565216890,
    "estimate": null,
    "estimate_forecast": null,
    "suite_id": 20832,
    "display_order": 6,
    "custom_preconds": "GIVEN\r\nThere is a Post Season game that is in the Live state AND the game is a Perfect Game AND set to display as two lines",
    "custom_steps": "WHEN\r\nThe user navigates to Scoreboard List View",
    "custom_expected": "THEN\r\nThe following elements should be displayed:\r\nhttps://zpl.io/VQQjp6x\r\n - Two Lines: Series Name, Game Info\r\n - Perfect Game text",
    "custom_steps_separated": [
      {
        "content": "",
        "expected": ""
      }
    ]
  },
  {
    "id": 1248479,
    "title": "Post Season - Live: Two Lines, with No Hitter",
    "section_id": 151712,
    "template_id": 1,
    "type_id": 4,
    "priority_id": 6,
    "milestone_id": null,
    "refs": null,
    "created_by": 171,
    "created_on": 1565199932,
    "updated_by": 188,
    "updated_on": 1565216899,
    "estimate": null,
    "estimate_forecast": null,
    "suite_id": 20832,
    "display_order": 7,
    "custom_preconds": "GIVEN\r\nThere is a Post Season game that is in the Live state AND the game is a No Hitter AND set to display as two lines",
    "custom_steps": "WHEN\r\nThe user navigates to Scoreboard List View",
    "custom_expected": "THEN\r\nThe following elements should be displayed:\r\nhttps://zpl.io/VQQjp6x\r\n - Two Lines: Series Name, Game Info\r\n - No Hitter text",
    "custom_steps_separated": null
  },
  {
    "id": 1248480,
    "title": "Pre-Game > Live",
    "section_id": 151713,
    "template_id": 1,
    "type_id": 4,
    "priority_id": 6,
    "milestone_id": null,
    "refs": null,
    "created_by": 171,
    "created_on": 1565199932,
    "updated_by": 188,
    "updated_on": 1565216915,
    "estimate": null,
    "estimate_forecast": null,
    "suite_id": 20832,
    "display_order": 1,
    "custom_preconds": "GIVEN\r\nThere is a game that is in the Pregame state AND the user has navigated to Scoreboard Card View",
    "custom_steps": "WHEN\r\nThe game state transitions to the Live state",
    "custom_expected": "THEN\r\nThe following elements should be displayed:\r\nhttps://zpl.io/VQQjp6x\r\n - Linescore\r\n - Scores\r\n - Bases\r\n - Pitch Count\r\n - Outs\r\n - Inning\r\n - Pitcher/Batter Matchup",
    "custom_steps_separated": null
  },
  {
    "id": 1248481,
    "title": "Live > Suspended",
    "section_id": 151713,
    "template_id": 1,
    "type_id": 4,
    "priority_id": 6,
    "milestone_id": null,
    "refs": null,
    "created_by": 171,
    "created_on": 1565199932,
    "updated_by": 188,
    "updated_on": 1565216926,
    "estimate": null,
    "estimate_forecast": null,
    "suite_id": 20832,
    "display_order": 2,
    "custom_preconds": "GIVEN\r\nThere is a game that is in the Live state AND the user has navigated to Scoreboard Card View",
    "custom_steps": "WHEN\r\nThe game state transitions to the Suspended state",
    "custom_expected": "THEN\r\nThe following elements should be displayed:\r\nhttps://zpl.io/VQQjp6x\r\n - Susp text displays",
    "custom_steps_separated": null
  },
  {
    "id": 1248482,
    "title": "Suspended > Resume",
    "section_id": 151713,
    "template_id": 1,
    "type_id": 4,
    "priority_id": 6,
    "milestone_id": null,
    "refs": null,
    "created_by": 171,
    "created_on": 1565199932,
    "updated_by": 188,
    "updated_on": 1565216937,
    "estimate": null,
    "estimate_forecast": null,
    "suite_id": 20832,
    "display_order": 3,
    "custom_preconds": "GIVEN\r\nThere is a game that is in the Suspended state AND the user has navigated to Scoreboard Card View",
    "custom_steps": "WHEN\r\nThe game state transitions back to the Live state",
    "custom_expected": "THEN\r\nThe following elements should be displayed:\r\nhttps://zpl.io/VQQjp6x\r\n - Linescore\r\n - Scores\r\n - Bases\r\n - Pitch Count\r\n - Outs\r\n - Inning\r\n - Pitcher/Batter Matchup",
    "custom_steps_separated": null
  },
  {
    "id": 1248483,
    "title": "Delay > Live",
    "section_id": 151713,
    "template_id": 1,
    "type_id": 4,
    "priority_id": 6,
    "milestone_id": null,
    "refs": null,
    "created_by": 171,
    "created_on": 1565199932,
    "updated_by": 188,
    "updated_on": 1565217024,
    "estimate": null,
    "estimate_forecast": null,
    "suite_id": 20832,
    "display_order": 4,
    "custom_preconds": "GIVEN\r\nThere is a game that is in the Delayed state AND the user has navigated to Scoreboard Card View",
    "custom_steps": "WHEN\r\nThe game state transitions to the Live state",
    "custom_expected": "\t\r\nTHEN\r\nThe following elements should be displayed:\r\nhttps://zpl.io/VQQjp6x\r\n- Linescore\r\n- Scores\r\n- Bases\r\n- Pitch Count\r\n- Outs\r\n- Inning\r\n- Pitcher/Batter Matchup",
    "custom_steps_separated": null
  },
  {
    "id": 1248484,
    "title": "Live > Final",
    "section_id": 151713,
    "template_id": 1,
    "type_id": 4,
    "priority_id": 6,
    "milestone_id": null,
    "refs": null,
    "created_by": 171,
    "created_on": 1565199932,
    "updated_by": 188,
    "updated_on": 1565217036,
    "estimate": null,
    "estimate_forecast": null,
    "suite_id": 20832,
    "display_order": 5,
    "custom_preconds": "GIVEN\r\nThere is a game that is in the Live state AND the user has navigated to Scoreboard Card View",
    "custom_steps": "WHEN\r\nThe game state transitions to the Final state",
    "custom_expected": "THEN\r\nThe following elements should be displayed:\r\nhttps://zpl.io/VQQjp6x\r\n - Final text displays\r\n - Winning/Losing/Save Pitcher\r\n - Final Score\r\n - Updated Team Records\r\n - Complete linescore for all innings played",
    "custom_steps_separated": null
  },
  {
    "id": 1248485,
    "title": "Card > List: Pregame",
    "section_id": 151715,
    "template_id": 1,
    "type_id": 4,
    "priority_id": 6,
    "milestone_id": null,
    "refs": null,
    "created_by": 171,
    "created_on": 1565199932,
    "updated_by": 188,
    "updated_on": 1565217054,
    "estimate": null,
    "estimate_forecast": null,
    "suite_id": 20832,
    "display_order": 1,
    "custom_preconds": "GIVEN\r\nThere is a game that is in the Pregame state AND the user has navigated to Scoreboard Card View AND the user has scrolled to the top of the page",
    "custom_steps": "WHEN\r\nThe user switches view to List View",
    "custom_expected": "THEN\r\nThe following elements should be displayed:\r\nhttps://zpl.io/VQQjp6x\r\n- Team Logos\r\n- Team Code\r\n- Team Records\r\n- First Pitch Gametime (local time zone support)\r\n- Probable Pitchers and Stats",
    "custom_steps_separated": null
  },
  {
    "id": 1248486,
    "title": "Card > Compact: Pregame",
    "section_id": 151715,
    "template_id": 1,
    "type_id": 4,
    "priority_id": 6,
    "milestone_id": null,
    "refs": null,
    "created_by": 171,
    "created_on": 1565199932,
    "updated_by": 188,
    "updated_on": 1565217064,
    "estimate": null,
    "estimate_forecast": null,
    "suite_id": 20832,
    "display_order": 2,
    "custom_preconds": "GIVEN\r\nThere is a game that is in the Pregame state AND the user has navigated to Scoreboard Card View AND the user has scrolled to the top of the page",
    "custom_steps": "WHEN\r\nThe user switches view to Compact View",
    "custom_expected": "THEN\r\nThe following elements should be displayed:\r\nhttps://zpl.io/VQQjp6x\r\n- Team Logos\r\n- Team Code\r\n- Team Records\r\n- First Pitch Gametime (local time zone support)\r\n- Probable Pitchers and Stats",
    "custom_steps_separated": null
  },
  {
    "id": 1248487,
    "title": "List > Card: Pregame",
    "section_id": 151715,
    "template_id": 1,
    "type_id": 4,
    "priority_id": 6,
    "milestone_id": null,
    "refs": null,
    "created_by": 171,
    "created_on": 1565199932,
    "updated_by": 188,
    "updated_on": 1565217085,
    "estimate": null,
    "estimate_forecast": null,
    "suite_id": 20832,
    "display_order": 3,
    "custom_preconds": "GIVEN\r\nThere is a game that is in the Pregame state AND the user has navigated to Scoreboard Card View AND the user has scrolled to the top of the page",
    "custom_steps": "WHEN\r\nThe user switches view to Card View",
    "custom_expected": "THEN\r\nThe following elements should be displayed:\r\nhttps://zpl.io/VQQjp6x\r\n- Team Logos\r\n- Team Code\r\n- Team Records\r\n- First Pitch Gametime (local time zone support)\r\n- Probable Pitchers and Stats",
    "custom_steps_separated": null
  },
  {
    "id": 1248488,
    "title": "List > Compact: Pregame",
    "section_id": 151715,
    "template_id": 1,
    "type_id": 4,
    "priority_id": 6,
    "milestone_id": null,
    "refs": null,
    "created_by": 171,
    "created_on": 1565199932,
    "updated_by": 188,
    "updated_on": 1565217227,
    "estimate": null,
    "estimate_forecast": null,
    "suite_id": 20832,
    "display_order": 4,
    "custom_preconds": "GIVEN\nThere is a game that is in the Pregame state AND the user has navigated to Scoreboard Card View AND the user has scrolled to the top of the page",
    "custom_steps": "WHEN\nThe user switches view to Compact View",
    "custom_expected": "THEN\r\nThe following elements should be displayed:\r\nhttps://zpl.io/VQQjp6x\r\n- Team Logos\r\n- Team Code\r\n- Team Records\r\n- First Pitch Gametime (local time zone support)\r\n- Probable Pitchers and Stats",
    "custom_steps_separated": null
  },
  {
    "id": 1248489,
    "title": "Compact > Card: Pregame",
    "section_id": 151715,
    "template_id": 1,
    "type_id": 4,
    "priority_id": 6,
    "milestone_id": null,
    "refs": null,
    "created_by": 171,
    "created_on": 1565199932,
    "updated_by": 188,
    "updated_on": 1565217227,
    "estimate": null,
    "estimate_forecast": null,
    "suite_id": 20832,
    "display_order": 5,
    "custom_preconds": "GIVEN\nThere is a game that is in the Pregame state AND the user has navigated to Scoreboard Compact View AND the user has scrolled to the top of the page",
    "custom_steps": "WHEN\nThe user switches view to Card View",
    "custom_expected": "THEN\r\nThe following elements should be displayed:\r\nhttps://zpl.io/VQQjp6x\r\n- Team Logos\r\n- Team Code\r\n- Team Records\r\n- First Pitch Gametime (local time zone support)\r\n- Probable Pitchers and Stats",
    "custom_steps_separated": null
  },
  {
    "id": 1248490,
    "title": "Compact > List: Pregame",
    "section_id": 151715,
    "template_id": 1,
    "type_id": 4,
    "priority_id": 6,
    "milestone_id": null,
    "refs": null,
    "created_by": 171,
    "created_on": 1565199932,
    "updated_by": 188,
    "updated_on": 1565217227,
    "estimate": null,
    "estimate_forecast": null,
    "suite_id": 20832,
    "display_order": 6,
    "custom_preconds": "GIVEN\nThere is a game that is in the Pregame state AND the user has navigated to Scoreboard Compact View AND the user has scrolled to the top of the page",
    "custom_steps": "WHEN\nThe user switches view to List View",
    "custom_expected": "THEN\r\nThe following elements should be displayed:\r\nhttps://zpl.io/VQQjp6x\r\n- Team Logos\r\n- Team Code\r\n- Team Records\r\n- First Pitch Gametime (local time zone support)\r\n- Probable Pitchers and Stats",
    "custom_steps_separated": null
  },
  {
    "id": 1248496,
    "title": "Compact > List: Live",
    "section_id": 151716,
    "template_id": 1,
    "type_id": 4,
    "priority_id": 6,
    "milestone_id": null,
    "refs": null,
    "created_by": 171,
    "created_on": 1565199932,
    "updated_by": 188,
    "updated_on": 1565217242,
    "estimate": null,
    "estimate_forecast": null,
    "suite_id": 20832,
    "display_order": 1,
    "custom_preconds": "GIVEN\nThere is a game that is in the Live state AND the user has navigated to Scoreboard Compact View AND the user has scrolled to the top of the page",
    "custom_steps": "WHEN\nThe user switches view to List View",
    "custom_expected": "THEN\r\nThe following elements should be displayed:\r\nhttps://zpl.io/VQQjp6x\r\n- Linescore\r\n- Scores\r\n- Bases\r\n- Pitch Count\r\n- Outs\r\n- Inning\r\n- Pitcher/Batter Matchup",
    "custom_steps_separated": null
  },
  {
    "id": 1248491,
    "title": "Card > List: Live",
    "section_id": 151716,
    "template_id": 1,
    "type_id": 4,
    "priority_id": 6,
    "milestone_id": null,
    "refs": null,
    "created_by": 171,
    "created_on": 1565199932,
    "updated_by": 188,
    "updated_on": 1565217242,
    "estimate": null,
    "estimate_forecast": null,
    "suite_id": 20832,
    "display_order": 2,
    "custom_preconds": "GIVEN\nThere is a game that is in the Live state AND the user has navigated to Scoreboard Card View AND the user has scrolled to the top of the page",
    "custom_steps": "WHEN\nThe user switches view to List View",
    "custom_expected": "THEN\r\nThe following elements should be displayed:\r\nhttps://zpl.io/VQQjp6x\r\n- Linescore\r\n- Scores\r\n- Bases\r\n- Pitch Count\r\n- Outs\r\n- Inning\r\n- Pitcher/Batter Matchup",
    "custom_steps_separated": null
  },
  {
    "id": 1248492,
    "title": "Card > Compact: Live",
    "section_id": 151716,
    "template_id": 1,
    "type_id": 4,
    "priority_id": 6,
    "milestone_id": null,
    "refs": null,
    "created_by": 171,
    "created_on": 1565199932,
    "updated_by": 188,
    "updated_on": 1565217242,
    "estimate": null,
    "estimate_forecast": null,
    "suite_id": 20832,
    "display_order": 3,
    "custom_preconds": "GIVEN\nThere is a game that is in the Live state AND the user has navigated to Scoreboard Card View AND the user has scrolled to the top of the page",
    "custom_steps": "WHEN\nThe user switches view to Compact View",
    "custom_expected": "THEN\r\nThe following elements should be displayed:\r\nhttps://zpl.io/VQQjp6x\r\n- Linescore\r\n- Scores\r\n- Bases\r\n- Pitch Count\r\n- Outs\r\n- Inning\r\n- Pitcher/Batter Matchup",
    "custom_steps_separated": null
  },
  {
    "id": 1248493,
    "title": "List > Card: Live",
    "section_id": 151716,
    "template_id": 1,
    "type_id": 4,
    "priority_id": 6,
    "milestone_id": null,
    "refs": null,
    "created_by": 171,
    "created_on": 1565199932,
    "updated_by": 188,
    "updated_on": 1565217242,
    "estimate": null,
    "estimate_forecast": null,
    "suite_id": 20832,
    "display_order": 4,
    "custom_preconds": "GIVEN\nThere is a game that is in the Live state AND the user has navigated to Scoreboard List View AND the user has scrolled to the top of the page",
    "custom_steps": "WHEN\nThe user switches view to Card View",
    "custom_expected": "THEN\r\nThe following elements should be displayed:\r\nhttps://zpl.io/VQQjp6x\r\n- Linescore\r\n- Scores\r\n- Bases\r\n- Pitch Count\r\n- Outs\r\n- Inning\r\n- Pitcher/Batter Matchup",
    "custom_steps_separated": null
  },
  {
    "id": 1248494,
    "title": "List > Compact: Live",
    "section_id": 151716,
    "template_id": 1,
    "type_id": 4,
    "priority_id": 6,
    "milestone_id": null,
    "refs": null,
    "created_by": 171,
    "created_on": 1565199932,
    "updated_by": 188,
    "updated_on": 1565217242,
    "estimate": null,
    "estimate_forecast": null,
    "suite_id": 20832,
    "display_order": 5,
    "custom_preconds": "GIVEN\nThere is a game that is in the Live state AND the user has navigated to Scoreboard List View AND the user has scrolled to the top of the page",
    "custom_steps": "WHEN\nThe user switches view to Compact View",
    "custom_expected": "THEN\r\nThe following elements should be displayed:\r\nhttps://zpl.io/VQQjp6x\r\n- Linescore\r\n- Scores\r\n- Bases\r\n- Pitch Count\r\n- Outs\r\n- Inning\r\n- Pitcher/Batter Matchup",
    "custom_steps_separated": null
  },
  {
    "id": 1248495,
    "title": "Compact > Card: Live",
    "section_id": 151716,
    "template_id": 1,
    "type_id": 4,
    "priority_id": 6,
    "milestone_id": null,
    "refs": null,
    "created_by": 171,
    "created_on": 1565199932,
    "updated_by": 188,
    "updated_on": 1565217242,
    "estimate": null,
    "estimate_forecast": null,
    "suite_id": 20832,
    "display_order": 6,
    "custom_preconds": "GIVEN\nThere is a game that is in the Live state AND the user has navigated to Scoreboard Compact View AND the user has scrolled to the top of the page",
    "custom_steps": "WHEN\nThe user switches view to Card View",
    "custom_expected": "THEN\r\nThe following elements should be displayed:\r\nhttps://zpl.io/VQQjp6x\r\n- Linescore\r\n- Scores\r\n- Bases\r\n- Pitch Count\r\n- Outs\r\n- Inning\r\n- Pitcher/Batter Matchup",
    "custom_steps_separated": null
  },
  {
    "id": 1248497,
    "title": "Card > List: Final",
    "section_id": 151717,
    "template_id": 1,
    "type_id": 4,
    "priority_id": 6,
    "milestone_id": null,
    "refs": null,
    "created_by": 171,
    "created_on": 1565199932,
    "updated_by": 188,
    "updated_on": 1565217259,
    "estimate": null,
    "estimate_forecast": null,
    "suite_id": 20832,
    "display_order": 2,
    "custom_preconds": "GIVEN\nThere is a game that is in the Final state AND the user has navigated to Scoreboard Card View AND the user has scrolled to the top of the page",
    "custom_steps": "WHEN\nThe user switches view to List View",
    "custom_expected": "THEN\r\nThe following elements should be displayed:\r\nhttps://zpl.io/VQQjp6x\r\n- Winning/Losing/Save Pitcher\r\n- Final Score\r\n- Updated Team Records\r\n- Complete linescore for all innings played\r\n",
    "custom_steps_separated": null
  },
  {
    "id": 1248498,
    "title": "Card > Compact: Final",
    "section_id": 151717,
    "template_id": 1,
    "type_id": 4,
    "priority_id": 6,
    "milestone_id": null,
    "refs": null,
    "created_by": 171,
    "created_on": 1565199932,
    "updated_by": 188,
    "updated_on": 1565217259,
    "estimate": null,
    "estimate_forecast": null,
    "suite_id": 20832,
    "display_order": 3,
    "custom_preconds": "GIVEN\nThere is a game that is in the Final state AND the user has navigated to Scoreboard Card View AND the user has scrolled to the top of the page",
    "custom_steps": "WHEN\nThe user switches view to Compact View",
    "custom_expected": "THEN\r\nThe following elements should be displayed:\r\nhttps://zpl.io/VQQjp6x\r\n- Winning/Losing/Save Pitcher\r\n- Final Score\r\n- Updated Team Records\r\n- Complete linescore for all innings played\r\n",
    "custom_steps_separated": null
  },
  {
    "id": 1248499,
    "title": "List > Card: Final",
    "section_id": 151717,
    "template_id": 1,
    "type_id": 4,
    "priority_id": 6,
    "milestone_id": null,
    "refs": null,
    "created_by": 171,
    "created_on": 1565199932,
    "updated_by": 188,
    "updated_on": 1565217259,
    "estimate": null,
    "estimate_forecast": null,
    "suite_id": 20832,
    "display_order": 4,
    "custom_preconds": "GIVEN\nThere is a game that is in the Final state AND the user has navigated to Scoreboard Card View AND the user has scrolled to the top of the page",
    "custom_steps": "WHEN\nThe user switches view to Card View",
    "custom_expected": "THEN\r\nThe following elements should be displayed:\r\nhttps://zpl.io/VQQjp6x\r\n- Winning/Losing/Save Pitcher\r\n- Final Score\r\n- Updated Team Records\r\n- Complete linescore for all innings played\r\n",
    "custom_steps_separated": null
  },
  {
    "id": 1248500,
    "title": "List > Compact: Final",
    "section_id": 151717,
    "template_id": 1,
    "type_id": 4,
    "priority_id": 6,
    "milestone_id": null,
    "refs": null,
    "created_by": 171,
    "created_on": 1565199932,
    "updated_by": 188,
    "updated_on": 1565217259,
    "estimate": null,
    "estimate_forecast": null,
    "suite_id": 20832,
    "display_order": 5,
    "custom_preconds": "GIVEN\nThere is a game that is in the Final state AND the user has navigated to Scoreboard Card View AND the user has scrolled to the top of the page",
    "custom_steps": "WHEN\nThe user switches view to Compact View",
    "custom_expected": "THEN\r\nThe following elements should be displayed:\r\nhttps://zpl.io/VQQjp6x\r\n- Winning/Losing/Save Pitcher\r\n- Final Score\r\n- Updated Team Records\r\n- Complete linescore for all innings played\r\n",
    "custom_steps_separated": null
  },
  {
    "id": 1248501,
    "title": "Compact > Card: Final",
    "section_id": 151717,
    "template_id": 1,
    "type_id": 4,
    "priority_id": 6,
    "milestone_id": null,
    "refs": null,
    "created_by": 171,
    "created_on": 1565199932,
    "updated_by": 188,
    "updated_on": 1565217259,
    "estimate": null,
    "estimate_forecast": null,
    "suite_id": 20832,
    "display_order": 6,
    "custom_preconds": "GIVEN\nThere is a game that is in the Final state AND the user has navigated to Scoreboard Compact View AND the user has scrolled to the top of the page",
    "custom_steps": "WHEN\nThe user switches view to Card View",
    "custom_expected": "THEN\r\nThe following elements should be displayed:\r\nhttps://zpl.io/VQQjp6x\r\n- Winning/Losing/Save Pitcher\r\n- Final Score\r\n- Updated Team Records\r\n- Complete linescore for all innings played\r\n",
    "custom_steps_separated": null
  },
  {
    "id": 1248502,
    "title": "Compact > List: Final",
    "section_id": 151717,
    "template_id": 1,
    "type_id": 4,
    "priority_id": 6,
    "milestone_id": null,
    "refs": null,
    "created_by": 171,
    "created_on": 1565199932,
    "updated_by": 188,
    "updated_on": 1565217259,
    "estimate": null,
    "estimate_forecast": null,
    "suite_id": 20832,
    "display_order": 7,
    "custom_preconds": "GIVEN\nThere is a game that is in the Final state AND the user has navigated to Scoreboard Compact View AND the user has scrolled to the top of the page",
    "custom_steps": "WHEN\nThe user switches view to List View",
    "custom_expected": "THEN\r\nThe following elements should be displayed:\r\nhttps://zpl.io/VQQjp6x\r\n- Winning/Losing/Save Pitcher\r\n- Final Score\r\n- Updated Team Records\r\n- Complete linescore for all innings played\r\n",
    "custom_steps_separated": null
  }
]