[
  {
    "id": 1217604,
    "title": "Club Q Admin has same functionality as Author",
    "section_id": 146522,
    "template_id": 1,
    "type_id": 4,
    "priority_id": 6,
    "milestone_id": null,
    "refs": null,
    "created_by": 108,
    "created_on": 1517439503,
    "updated_by": 108,
    "updated_on": 1517439507,
    "estimate": null,
    "estimate_forecast": null,
    "suite_id": 20319,
    "display_order": 1,
    "custom_preconds": null,
    "custom_steps": null,
    "custom_expected": null,
    "custom_steps_separated": null
  },
  {
    "id": 1217606,
    "title": "Club Q Admin - first-level approval",
    "section_id": 146522,
    "template_id": 1,
    "type_id": 4,
    "priority_id": 6,
    "milestone_id": null,
    "refs": null,
    "created_by": 108,
    "created_on": 1517439535,
    "updated_by": 108,
    "updated_on": 1517439574,
    "estimate": null,
    "estimate_forecast": null,
    "suite_id": 20319,
    "display_order": 2,
    "custom_preconds": "GIVEN that user is a Club Questionnaire Admin",
    "custom_steps": null,
    "custom_expected": "THEN user has the right of first-level approval for all questionnaires created within their Club.",
    "custom_steps_separated": null
  },
  {
    "id": 1217609,
    "title": "Club Q Admin - request Central Office approval",
    "section_id": 146522,
    "template_id": 1,
    "type_id": 4,
    "priority_id": 6,
    "milestone_id": null,
    "refs": null,
    "created_by": 108,
    "created_on": 1517439897,
    "updated_by": 108,
    "updated_on": 1517440223,
    "estimate": null,
    "estimate_forecast": null,
    "suite_id": 20319,
    "display_order": 3,
    "custom_preconds": "GIVEN that Admin has approved a questionnaire",
    "custom_steps": null,
    "custom_expected": "THEN Admin can request Central Office to review the questionnaire.",
    "custom_steps_separated": null
  },
  {
    "id": 1217605,
    "title": "Author has same functionality as Scout",
    "section_id": 146523,
    "template_id": 1,
    "type_id": 4,
    "priority_id": 6,
    "milestone_id": null,
    "refs": null,
    "created_by": 108,
    "created_on": 1517439519,
    "updated_by": 108,
    "updated_on": 1518719662,
    "estimate": null,
    "estimate_forecast": null,
    "suite_id": 20319,
    "display_order": 1,
    "custom_preconds": null,
    "custom_steps": null,
    "custom_expected": null,
    "custom_steps_separated": null
  },
  {
    "id": 1217616,
    "title": "Author cannot use tablet",
    "section_id": 146523,
    "template_id": 1,
    "type_id": 4,
    "priority_id": 6,
    "milestone_id": null,
    "refs": "PROSPECT-120",
    "created_by": 108,
    "created_on": 1517441359,
    "updated_by": 108,
    "updated_on": 1520529508,
    "estimate": null,
    "estimate_forecast": null,
    "suite_id": 20319,
    "display_order": 2,
    "custom_preconds": "GIVEN that Author is drafting a questionnaire\r\nAND Author is using a tablet\r\n",
    "custom_steps": "WHEN Author taps questionnaire",
    "custom_expected": "THEN a popup appears that reads: \r\nWe've detected that you're using a device which supports touch interaction. Touch interaction is not supported on the Questionnaire creation tool.\r\nAND the popup appears over the questionnaire dropdown\r\nAND questionnaire functions are disabled.",
    "custom_steps_separated": null
  },
  {
    "id": 1217607,
    "title": "Author drafts questionnaire",
    "section_id": 146523,
    "template_id": 1,
    "type_id": 4,
    "priority_id": 6,
    "milestone_id": null,
    "refs": "PROSPECT-32, PROSPECT-36, PROSPECT-63",
    "created_by": 108,
    "created_on": 1517439847,
    "updated_by": 108,
    "updated_on": 1518719679,
    "estimate": null,
    "estimate_forecast": null,
    "suite_id": 20319,
    "display_order": 3,
    "custom_preconds": null,
    "custom_steps": null,
    "custom_expected": null,
    "custom_steps_separated": null
  },
  {
    "id": 1217608,
    "title": "Author requests Admin approval",
    "section_id": 146523,
    "template_id": 1,
    "type_id": 4,
    "priority_id": 6,
    "milestone_id": null,
    "refs": null,
    "created_by": 108,
    "created_on": 1517439873,
    "updated_by": 108,
    "updated_on": 1518719688,
    "estimate": null,
    "estimate_forecast": null,
    "suite_id": 20319,
    "display_order": 5,
    "custom_preconds": "GIVEN that Author has completed a questionnaire",
    "custom_steps": null,
    "custom_expected": "THEN Author can request their Club Questionnaire Admin to review the questionnaire.",
    "custom_steps_separated": null
  },
  {
    "id": 1217610,
    "title": "Author sees Central Office review",
    "section_id": 146523,
    "template_id": 1,
    "type_id": 4,
    "priority_id": 6,
    "milestone_id": null,
    "refs": null,
    "created_by": 108,
    "created_on": 1517439945,
    "updated_by": 108,
    "updated_on": 1518719700,
    "estimate": null,
    "estimate_forecast": null,
    "suite_id": 20319,
    "display_order": 6,
    "custom_preconds": "GIVEN that Club has submitted a questionnaire for Central Office to review\r\nAND Central Office has completed its review",
    "custom_steps": null,
    "custom_expected": "THEN Author can see the Central Office's review of the questionnaire.",
    "custom_steps_separated": null
  },
  {
    "id": 1217611,
    "title": "Author replies to Central Office review",
    "section_id": 146523,
    "template_id": 1,
    "type_id": 4,
    "priority_id": 6,
    "milestone_id": null,
    "refs": "PROSPECT-29",
    "created_by": 108,
    "created_on": 1517439964,
    "updated_by": 108,
    "updated_on": 1518719723,
    "estimate": null,
    "estimate_forecast": null,
    "suite_id": 20319,
    "display_order": 7,
    "custom_preconds": "GIVEN that Club has submitted a questionnaire for Central Office to review\r\nAND Central Office has completed its review",
    "custom_steps": "WHEN Author sees Central Office's review",
    "custom_expected": "THEN Author can comment on the review.",
    "custom_steps_separated": null
  },
  {
    "id": 1217613,
    "title": "Review is BOC-Club only, not within Club",
    "section_id": 146523,
    "template_id": 1,
    "type_id": 4,
    "priority_id": 6,
    "milestone_id": null,
    "refs": "PROSPECT-23",
    "created_by": 108,
    "created_on": 1517440005,
    "updated_by": 108,
    "updated_on": 1517440479,
    "estimate": null,
    "estimate_forecast": null,
    "suite_id": 20319,
    "display_order": 9,
    "custom_preconds": "GIVEN that Author has created a questionnaire\r\n",
    "custom_steps": null,
    "custom_expected": "THEN the Author's Club Questionnaire Admin can review the questionnaire\r\nAND Central Office can review the questionnaire\r\nAND no other member of the Author's Club can review the questionnaire.",
    "custom_steps_separated": null
  },
  {
    "id": 1217797,
    "title": "Test responsiveness",
    "section_id": 146523,
    "template_id": 1,
    "type_id": 4,
    "priority_id": 6,
    "milestone_id": null,
    "refs": null,
    "created_by": 108,
    "created_on": 1517691933,
    "updated_by": 108,
    "updated_on": 1517691975,
    "estimate": null,
    "estimate_forecast": null,
    "suite_id": 20319,
    "display_order": 10,
    "custom_preconds": null,
    "custom_steps": null,
    "custom_expected": null,
    "custom_steps_separated": null
  },
  {
    "id": 1219661,
    "title": "Author sees index screen of questionnaires",
    "section_id": 146535,
    "template_id": 1,
    "type_id": 4,
    "priority_id": 6,
    "milestone_id": null,
    "refs": "PROSPECT-107",
    "created_by": 108,
    "created_on": 1518719789,
    "updated_by": 108,
    "updated_on": 1518719810,
    "estimate": null,
    "estimate_forecast": null,
    "suite_id": 20319,
    "display_order": 1,
    "custom_preconds": null,
    "custom_steps": null,
    "custom_expected": null,
    "custom_steps_separated": null
  },
  {
    "id": 1219373,
    "title": "Author chooses type of questionnaire",
    "section_id": 146535,
    "template_id": 1,
    "type_id": 4,
    "priority_id": 4,
    "milestone_id": null,
    "refs": "PROSPECT-91",
    "created_by": 108,
    "created_on": 1518634737,
    "updated_by": 108,
    "updated_on": 1518634843,
    "estimate": null,
    "estimate_forecast": null,
    "suite_id": 20319,
    "display_order": 2,
    "custom_preconds": "GIVEN that user is a Club Questionnaire Author",
    "custom_steps": "WHEN author creates a questionnaire",
    "custom_expected": "THEN author can choose the type of questionnaire\r\nAND one choice is Common Application Questionnaire\r\nAND one choice is Medical Questionnaire\r\n[AND one choice is Club-Specific?]",
    "custom_steps_separated": null
  },
  {
    "id": 1219372,
    "title": "Author chooses language for questionnaire",
    "section_id": 146535,
    "template_id": 1,
    "type_id": 4,
    "priority_id": 6,
    "milestone_id": null,
    "refs": "PROSPECT-90",
    "created_by": 108,
    "created_on": 1518634663,
    "updated_by": 108,
    "updated_on": 1518634689,
    "estimate": null,
    "estimate_forecast": null,
    "suite_id": 20319,
    "display_order": 3,
    "custom_preconds": null,
    "custom_steps": null,
    "custom_expected": null,
    "custom_steps_separated": null
  },
  {
    "id": 1219374,
    "title": "Author chooses school level for questionnaire",
    "section_id": 146535,
    "template_id": 1,
    "type_id": 4,
    "priority_id": 6,
    "milestone_id": null,
    "refs": "PROSPECT-92",
    "created_by": 108,
    "created_on": 1518635579,
    "updated_by": 108,
    "updated_on": 1518635652,
    "estimate": null,
    "estimate_forecast": null,
    "suite_id": 20319,
    "display_order": 4,
    "custom_preconds": "GIVEN that user is a Club Questionnaire Author",
    "custom_steps": "WHEN author creates a questionnaire",
    "custom_expected": "THEN author chooses the school level\r\nAND one choice is high school\r\nAND one choice is college\r\nAND one choice is both.",
    "custom_steps_separated": null
  },
  {
    "id": 1217663,
    "title": "Author chooses among questionnaires",
    "section_id": 146535,
    "template_id": 1,
    "type_id": 4,
    "priority_id": 6,
    "milestone_id": null,
    "refs": "PROSPECT-44, PROSPECT-48, https://wiki.mlbam.com/display/ECT/Individual+Functional+Requirements",
    "created_by": 108,
    "created_on": 1517447438,
    "updated_by": 108,
    "updated_on": 1517448020,
    "estimate": null,
    "estimate_forecast": null,
    "suite_id": 20319,
    "display_order": 5,
    "custom_preconds": "GIVEN that Author is on the home page\r\nAND nav has appeared",
    "custom_steps": "WHEN Author clicks on Questionnaires in the nav",
    "custom_expected": "THEN dropdown appears\r\nAND dropdown is limited to 6 items \r\nAND items in the dropdown are:\r\nCreate New Questionnaire\r\nReview AAA Questionnaires (x)\r\n[where AAA = Club's 3-letter abbreviation]\r\n[where x = number of Club's questionnaires]\r\nCurrent Year Common Questionnaire\r\nCurrent Year Medical Questionnaire\r\nPrevious Year Common Questionnaire\r\nPrevious Year Medical Questionnaire\r\n\r\nAND list does not include Club-Specific questionnaires.",
    "custom_steps_separated": null
  },
  {
    "id": 1217666,
    "title": "Author copies a questionnaire",
    "section_id": 146535,
    "template_id": 1,
    "type_id": 4,
    "priority_id": 6,
    "milestone_id": null,
    "refs": "PROSPECT-52, PROSPECT-83, https://wiki.mlbam.com/display/ECT/Individual+Functional+Requirements",
    "created_by": 108,
    "created_on": 1517448136,
    "updated_by": 108,
    "updated_on": 1517448292,
    "estimate": null,
    "estimate_forecast": null,
    "suite_id": 20319,
    "display_order": 8,
    "custom_preconds": "GIVEN that Author is copying a questionnaire",
    "custom_steps": null,
    "custom_expected": "THEN Author can only copy a questionnaire generated within Author's own Club.",
    "custom_steps_separated": null
  },
  {
    "id": 1217665,
    "title": "Copy questionnaire toggle",
    "section_id": 146535,
    "template_id": 1,
    "type_id": 4,
    "priority_id": 6,
    "milestone_id": null,
    "refs": "PROSPECT-52, PROSPECT-83, https://wiki.mlbam.com/display/ECT/Individual+Functional+Requirements",
    "created_by": 108,
    "created_on": 1517448128,
    "updated_by": 108,
    "updated_on": 1517448299,
    "estimate": null,
    "estimate_forecast": null,
    "suite_id": 20319,
    "display_order": 9,
    "custom_preconds": "GIVEN that Author is copying a questionnaire",
    "custom_steps": null,
    "custom_expected": "THEN the Copy toggle appears\r\nAND the toggle shows 2 years of questionnaires by default\r\nAND toggle is configurable to show more.",
    "custom_steps_separated": null
  },
  {
    "id": 1219662,
    "title": "Author views preview of questionnaire",
    "section_id": 146535,
    "template_id": 1,
    "type_id": 4,
    "priority_id": 6,
    "milestone_id": null,
    "refs": "PROSPECT-108",
    "created_by": 108,
    "created_on": 1518719860,
    "updated_by": 108,
    "updated_on": 1518719875,
    "estimate": null,
    "estimate_forecast": null,
    "suite_id": 20319,
    "display_order": 10,
    "custom_preconds": null,
    "custom_steps": null,
    "custom_expected": null,
    "custom_steps_separated": null
  },
  {
    "id": 1219663,
    "title": "Author downloads .pdf of questionnaire",
    "section_id": 146535,
    "template_id": 1,
    "type_id": 4,
    "priority_id": 6,
    "milestone_id": null,
    "refs": "PROSPECT-109",
    "created_by": 108,
    "created_on": 1518719918,
    "updated_by": 108,
    "updated_on": 1518719947,
    "estimate": null,
    "estimate_forecast": null,
    "suite_id": 20319,
    "display_order": 11,
    "custom_preconds": null,
    "custom_steps": null,
    "custom_expected": null,
    "custom_steps_separated": null
  },
  {
    "id": 1217664,
    "title": "Current questionnaire is unlocked",
    "section_id": 146535,
    "template_id": 1,
    "type_id": 4,
    "priority_id": 6,
    "milestone_id": null,
    "refs": "PROSPECT-48, https://wiki.mlbam.com/display/ECT/Individual+Functional+Requirements",
    "created_by": 108,
    "created_on": 1517448032,
    "updated_by": 108,
    "updated_on": 1518719848,
    "estimate": null,
    "estimate_forecast": null,
    "suite_id": 20319,
    "display_order": 12,
    "custom_preconds": "GIVEN that Author has selected the Questionnaires option in the nav",
    "custom_steps": "WHEN the current year's questionnaire is unlocked",
    "custom_expected": "THEN that item is grayed out in the dropdown list.",
    "custom_steps_separated": null
  },
  {
    "id": 1219658,
    "title": "Author changes status of questionnaire to Draft",
    "section_id": 146535,
    "template_id": 1,
    "type_id": 4,
    "priority_id": 6,
    "milestone_id": null,
    "refs": "PROSPECT-97, PROSPECT-99, PROSPECT-101, PROSPECT-104",
    "created_by": 108,
    "created_on": 1518719263,
    "updated_by": 108,
    "updated_on": 1518719479,
    "estimate": null,
    "estimate_forecast": null,
    "suite_id": 20319,
    "display_order": 14,
    "custom_preconds": "GIVEN that Author is creating a questionnaire\r\n",
    "custom_steps": "WHEN Author moves the questionnaire into Draft status\r\n",
    "custom_expected": "THEN DP system records the date and time questionnaire was moved into Draft status\r\nAND system tracks all the edits made after that date and time\r\nAND system displays edits made since 2 previous status changes.",
    "custom_steps_separated": null
  },
  {
    "id": 1219660,
    "title": "Q status change triggers email",
    "section_id": 146535,
    "template_id": 1,
    "type_id": 4,
    "priority_id": 6,
    "milestone_id": null,
    "refs": "PROSPECT-106",
    "created_by": 108,
    "created_on": 1518719570,
    "updated_by": 108,
    "updated_on": 1518719902,
    "estimate": null,
    "estimate_forecast": null,
    "suite_id": 20319,
    "display_order": 15,
    "custom_preconds": "GIVEN that Author is creating a questionnaire",
    "custom_steps": "WHEN Author changes the status of the questionnaire",
    "custom_expected": "THEN an email about the change is sent to relevant users.",
    "custom_steps_separated": null
  },
  {
    "id": 1219659,
    "title": "Author sees info for available statuses",
    "section_id": 146535,
    "template_id": 1,
    "type_id": 4,
    "priority_id": 6,
    "milestone_id": null,
    "refs": "PROSPECT-105",
    "created_by": 108,
    "created_on": 1518719296,
    "updated_by": 108,
    "updated_on": 1518719542,
    "estimate": null,
    "estimate_forecast": null,
    "suite_id": 20319,
    "display_order": 16,
    "custom_preconds": "GIVEN that Author is creating a questionnaire",
    "custom_steps": "WHEN Author changes the status of the questionnaire",
    "custom_expected": "THEN the correct buttons and labels for all available statuses are displayed.",
    "custom_steps_separated": null
  },
  {
    "id": 1217801,
    "title": "Test responsiveness",
    "section_id": 146535,
    "template_id": 1,
    "type_id": 4,
    "priority_id": 6,
    "milestone_id": null,
    "refs": null,
    "created_by": 108,
    "created_on": 1517691989,
    "updated_by": 108,
    "updated_on": 1518719852,
    "estimate": null,
    "estimate_forecast": null,
    "suite_id": 20319,
    "display_order": 17,
    "custom_preconds": null,
    "custom_steps": null,
    "custom_expected": null,
    "custom_steps_separated": null
  },
  {
    "id": 1217667,
    "title": "Author creates a questionnaire page",
    "section_id": 146536,
    "template_id": 1,
    "type_id": 4,
    "priority_id": 6,
    "milestone_id": null,
    "refs": "PROSPECT-32, PROSPECT-64",
    "created_by": 108,
    "created_on": 1517448367,
    "updated_by": 108,
    "updated_on": 1517448407,
    "estimate": null,
    "estimate_forecast": null,
    "suite_id": 20319,
    "display_order": 1,
    "custom_preconds": null,
    "custom_steps": null,
    "custom_expected": null,
    "custom_steps_separated": null
  },
  {
    "id": 1217668,
    "title": "Author deletes a questionnaire page",
    "section_id": 146536,
    "template_id": 1,
    "type_id": 4,
    "priority_id": 6,
    "milestone_id": null,
    "refs": "PROSPECT-32, PROSPECT-56, PROSPECT-79",
    "created_by": 108,
    "created_on": 1517448373,
    "updated_by": 108,
    "updated_on": 1517450423,
    "estimate": null,
    "estimate_forecast": null,
    "suite_id": 20319,
    "display_order": 2,
    "custom_preconds": null,
    "custom_steps": null,
    "custom_expected": null,
    "custom_steps_separated": null
  },
  {
    "id": 1217669,
    "title": "Delete page warning",
    "section_id": 146536,
    "template_id": 1,
    "type_id": 4,
    "priority_id": 6,
    "milestone_id": null,
    "refs": "PROSPECT-56",
    "created_by": 108,
    "created_on": 1517448440,
    "updated_by": 108,
    "updated_on": 1517448528,
    "estimate": null,
    "estimate_forecast": null,
    "suite_id": 20319,
    "display_order": 3,
    "custom_preconds": "GIVEN that Author is creating a questionnaire page\r\n",
    "custom_steps": "WHEN Author chooses to delete the page",
    "custom_expected": "THEN a popup appears that reads: You are about to delete this page and any questions associated with it.\r\nAND popup gives the option to continue deletion\r\nAND popup gives the option to cancel deletion.",
    "custom_steps_separated": null
  },
  {
    "id": 1217699,
    "title": "Author edits questionnaire page title",
    "section_id": 146536,
    "template_id": 1,
    "type_id": 4,
    "priority_id": 6,
    "milestone_id": null,
    "refs": "PROSPECT-32, PROSPECT-80",
    "created_by": 108,
    "created_on": 1517450403,
    "updated_by": 108,
    "updated_on": 1517450550,
    "estimate": null,
    "estimate_forecast": null,
    "suite_id": 20319,
    "display_order": 4,
    "custom_preconds": null,
    "custom_steps": null,
    "custom_expected": null,
    "custom_steps_separated": null
  },
  {
    "id": 1217697,
    "title": "Author expands questionnaire page",
    "section_id": 146536,
    "template_id": 1,
    "type_id": 4,
    "priority_id": 6,
    "milestone_id": null,
    "refs": "PROSPECT-32, PROSPECT-78",
    "created_by": 108,
    "created_on": 1517450383,
    "updated_by": 108,
    "updated_on": 1517450522,
    "estimate": null,
    "estimate_forecast": null,
    "suite_id": 20319,
    "display_order": 6,
    "custom_preconds": null,
    "custom_steps": null,
    "custom_expected": null,
    "custom_steps_separated": null
  },
  {
    "id": 1217698,
    "title": "Author collapses questionnaire page",
    "section_id": 146536,
    "template_id": 1,
    "type_id": 4,
    "priority_id": 6,
    "milestone_id": null,
    "refs": "PROSPECT-32, PROSPECT-78",
    "created_by": 108,
    "created_on": 1517450391,
    "updated_by": 108,
    "updated_on": 1517450529,
    "estimate": null,
    "estimate_forecast": null,
    "suite_id": 20319,
    "display_order": 7,
    "custom_preconds": null,
    "custom_steps": null,
    "custom_expected": null,
    "custom_steps_separated": null
  },
  {
    "id": 1217696,
    "title": "Columns exceed page width",
    "section_id": 146536,
    "template_id": 1,
    "type_id": 4,
    "priority_id": 6,
    "milestone_id": null,
    "refs": "PROSPECT-56",
    "created_by": 108,
    "created_on": 1517450374,
    "updated_by": 108,
    "updated_on": 1517450554,
    "estimate": null,
    "estimate_forecast": null,
    "suite_id": 20319,
    "display_order": 8,
    "custom_preconds": "GIVEN that Author is creating a questionnaire",
    "custom_steps": "WHEN the number of columns on a page exceeds the page width",
    "custom_expected": "THEN a horizontal scroll bar appears\r\nAND the scroll bar is functional.",
    "custom_steps_separated": null
  },
  {
    "id": 1217802,
    "title": "Test responsiveness",
    "section_id": 146536,
    "template_id": 1,
    "type_id": 4,
    "priority_id": 6,
    "milestone_id": null,
    "refs": null,
    "created_by": 108,
    "created_on": 1517691993,
    "updated_by": 108,
    "updated_on": 1517691993,
    "estimate": null,
    "estimate_forecast": null,
    "suite_id": 20319,
    "display_order": 9,
    "custom_preconds": null,
    "custom_steps": null,
    "custom_expected": null,
    "custom_steps_separated": null
  },
  {
    "id": 1217671,
    "title": "Question Type has instructions",
    "section_id": 146537,
    "template_id": 1,
    "type_id": 4,
    "priority_id": 6,
    "milestone_id": null,
    "refs": "PROSPECT-49, PROSPECT-56",
    "created_by": 108,
    "created_on": 1517448635,
    "updated_by": 108,
    "updated_on": 1517448718,
    "estimate": null,
    "estimate_forecast": null,
    "suite_id": 20319,
    "display_order": 1,
    "custom_preconds": "GIVEN Author is creating a questionnaire",
    "custom_steps": null,
    "custom_expected": "THEN underneath Question Type is a message:\r\nClick [on] any icon to add it to your questionnaire.\r\n\r\nAND message is horizontally centered beneath Question Type.",
    "custom_steps_separated": null
  },
  {
    "id": 1217670,
    "title": "Author chooses question type",
    "section_id": 146537,
    "template_id": 1,
    "type_id": 4,
    "priority_id": 6,
    "milestone_id": null,
    "refs": "PROSPECT-49",
    "created_by": 108,
    "created_on": 1517448619,
    "updated_by": 108,
    "updated_on": 1517448792,
    "estimate": null,
    "estimate_forecast": null,
    "suite_id": 20319,
    "display_order": 2,
    "custom_preconds": "GIVEN that Author is creating a questionnaire",
    "custom_steps": "WHEN Author clicks on Question Type",
    "custom_expected": "THEN popup appears with icons and labels indicating all the possible question types.",
    "custom_steps_separated": null
  },
  {
    "id": 1217672,
    "title": "No limit to number of questions",
    "section_id": 146537,
    "template_id": 1,
    "type_id": 4,
    "priority_id": 6,
    "milestone_id": null,
    "refs": "PROSPECT-56",
    "created_by": 108,
    "created_on": 1517448836,
    "updated_by": 108,
    "updated_on": 1517448898,
    "estimate": null,
    "estimate_forecast": null,
    "suite_id": 20319,
    "display_order": 3,
    "custom_preconds": "GIVEN that Author is creating a questionnaire\r\nAND the questionnaire is not a Club-Specific questionnaire",
    "custom_steps": null,
    "custom_expected": "THEN Author can add an unlimited number of questions to the questionnaire.",
    "custom_steps_separated": null
  },
  {
    "id": 1217614,
    "title": "Club-Specific Questionnaire: limit is 20 questions",
    "section_id": 146537,
    "template_id": 1,
    "type_id": 4,
    "priority_id": 4,
    "milestone_id": null,
    "refs": null,
    "created_by": 108,
    "created_on": 1517440080,
    "updated_by": 108,
    "updated_on": 1517448851,
    "estimate": null,
    "estimate_forecast": null,
    "suite_id": 20319,
    "display_order": 4,
    "custom_preconds": "GIVEN that Author is creating a Club-Specific questionnaire",
    "custom_steps": null,
    "custom_expected": "THEN questionnaire is limited to 20 questions.",
    "custom_steps_separated": null
  },
  {
    "id": 1217673,
    "title": "Questions are numbered",
    "section_id": 146537,
    "template_id": 1,
    "type_id": 4,
    "priority_id": 6,
    "milestone_id": null,
    "refs": "PROSPECT-26",
    "created_by": 108,
    "created_on": 1517448919,
    "updated_by": 108,
    "updated_on": 1517449107,
    "estimate": null,
    "estimate_forecast": null,
    "suite_id": 20319,
    "display_order": 5,
    "custom_preconds": "GIVEN that Author is creating a questionnaire",
    "custom_steps": null,
    "custom_expected": "THEN created questions are automatically numbered\r\nAND numbering automatically adjusts when questions are moved around.",
    "custom_steps_separated": null
  },
  {
    "id": 1217674,
    "title": "Author groups questions",
    "section_id": 146537,
    "template_id": 1,
    "type_id": 4,
    "priority_id": 6,
    "milestone_id": null,
    "refs": null,
    "created_by": 108,
    "created_on": 1517448924,
    "updated_by": 108,
    "updated_on": 1517448935,
    "estimate": null,
    "estimate_forecast": null,
    "suite_id": 20319,
    "display_order": 6,
    "custom_preconds": null,
    "custom_steps": null,
    "custom_expected": null,
    "custom_steps_separated": null
  },
  {
    "id": 1217695,
    "title": "Author re-orders questions",
    "section_id": 146537,
    "template_id": 1,
    "type_id": 4,
    "priority_id": 6,
    "milestone_id": null,
    "refs": "PROSPECT-32, PROSPECT-77",
    "created_by": 108,
    "created_on": 1517449578,
    "updated_by": 108,
    "updated_on": 1517449603,
    "estimate": null,
    "estimate_forecast": null,
    "suite_id": 20319,
    "display_order": 7,
    "custom_preconds": null,
    "custom_steps": null,
    "custom_expected": null,
    "custom_steps_separated": null
  },
  {
    "id": 1217675,
    "title": "Author copies a question",
    "section_id": 146537,
    "template_id": 1,
    "type_id": 4,
    "priority_id": 6,
    "milestone_id": null,
    "refs": "PROSPECT-58, PROSPECT-84",
    "created_by": 108,
    "created_on": 1517448941,
    "updated_by": 108,
    "updated_on": 1517449174,
    "estimate": null,
    "estimate_forecast": null,
    "suite_id": 20319,
    "display_order": 8,
    "custom_preconds": "GIVEN that Author is creating a questionnaire",
    "custom_steps": "WHEN Author copies a question",
    "custom_expected": "THEN the copied question appears just below the original question.",
    "custom_steps_separated": null
  },
  {
    "id": 1217676,
    "title": "Author adds questions to different pages",
    "section_id": 146537,
    "template_id": 1,
    "type_id": 4,
    "priority_id": 6,
    "milestone_id": null,
    "refs": "PROSPECT-61",
    "created_by": 108,
    "created_on": 1517448964,
    "updated_by": 108,
    "updated_on": 1517449191,
    "estimate": null,
    "estimate_forecast": null,
    "suite_id": 20319,
    "display_order": 9,
    "custom_preconds": null,
    "custom_steps": null,
    "custom_expected": null,
    "custom_steps_separated": null
  },
  {
    "id": 1217677,
    "title": "Author adds conditional question",
    "section_id": 146537,
    "template_id": 1,
    "type_id": 4,
    "priority_id": 6,
    "milestone_id": null,
    "refs": "PROSPECT-26",
    "created_by": 108,
    "created_on": 1517448973,
    "updated_by": 108,
    "updated_on": 1517449257,
    "estimate": null,
    "estimate_forecast": null,
    "suite_id": 20319,
    "display_order": 10,
    "custom_preconds": "GIVEN that Author is creating a questionnaire",
    "custom_steps": "WHEN Author adds a conditional question",
    "custom_expected": "THEN answering its parent question produces the conditional question\r\nAND the conditional question is lettered instead of numbered.",
    "custom_steps_separated": null
  },
  {
    "id": 1217678,
    "title": "Author copies conditional question",
    "section_id": 146537,
    "template_id": 1,
    "type_id": 4,
    "priority_id": 6,
    "milestone_id": null,
    "refs": "PROSPECT-56",
    "created_by": 108,
    "created_on": 1517448983,
    "updated_by": 108,
    "updated_on": 1517449362,
    "estimate": null,
    "estimate_forecast": null,
    "suite_id": 20319,
    "display_order": 11,
    "custom_preconds": null,
    "custom_steps": null,
    "custom_expected": null,
    "custom_steps_separated": null
  },
  {
    "id": 1217679,
    "title": "Author moves conditional question",
    "section_id": 146537,
    "template_id": 1,
    "type_id": 4,
    "priority_id": 6,
    "milestone_id": null,
    "refs": "PROSPECT-56",
    "created_by": 108,
    "created_on": 1517448990,
    "updated_by": 108,
    "updated_on": 1517449368,
    "estimate": null,
    "estimate_forecast": null,
    "suite_id": 20319,
    "display_order": 12,
    "custom_preconds": null,
    "custom_steps": null,
    "custom_expected": null,
    "custom_steps_separated": null
  },
  {
    "id": 1217680,
    "title": "Author deletes conditional question",
    "section_id": 146537,
    "template_id": 1,
    "type_id": 4,
    "priority_id": 6,
    "milestone_id": null,
    "refs": "PROSPECT-56",
    "created_by": 108,
    "created_on": 1517448998,
    "updated_by": 108,
    "updated_on": 1517449375,
    "estimate": null,
    "estimate_forecast": null,
    "suite_id": 20319,
    "display_order": 13,
    "custom_preconds": null,
    "custom_steps": null,
    "custom_expected": null,
    "custom_steps_separated": null
  },
  {
    "id": 1217681,
    "title": "Author adds an \"Other\" option to a question",
    "section_id": 146537,
    "template_id": 1,
    "type_id": 4,
    "priority_id": 6,
    "milestone_id": null,
    "refs": "PROSPECT-29",
    "created_by": 108,
    "created_on": 1517449017,
    "updated_by": 108,
    "updated_on": 1517449344,
    "estimate": null,
    "estimate_forecast": null,
    "suite_id": 20319,
    "display_order": 14,
    "custom_preconds": "GIVEN that Author is creating a questionnaire\r\nAND Author is creating a multiple-choice question",
    "custom_steps": "WHEN Author chooses \"Other\" as one option of the multiple-choice",
    "custom_expected": "THEN selecting Other will open a conditional question.",
    "custom_steps_separated": null
  },
  {
    "id": 1217682,
    "title": "Author creates single-answer question",
    "section_id": 146537,
    "template_id": 1,
    "type_id": 4,
    "priority_id": 6,
    "milestone_id": null,
    "refs": "PROSPECT-32, PROSPECT-65",
    "created_by": 108,
    "created_on": 1517449448,
    "updated_by": 108,
    "updated_on": 1517450204,
    "estimate": null,
    "estimate_forecast": null,
    "suite_id": 20319,
    "display_order": 15,
    "custom_preconds": "GIVEN that Author is creating a questionnaire\r\nAND Author is creating a single-answer question",
    "custom_steps": null,
    "custom_expected": "THEN question is formed with radio buttons.",
    "custom_steps_separated": null
  },
  {
    "id": 1217683,
    "title": "Author creates date question",
    "section_id": 146537,
    "template_id": 1,
    "type_id": 4,
    "priority_id": 6,
    "milestone_id": null,
    "refs": "PROSPECT-32, PROSPECT-66",
    "created_by": 108,
    "created_on": 1517449453,
    "updated_by": 108,
    "updated_on": 1517450227,
    "estimate": null,
    "estimate_forecast": null,
    "suite_id": 20319,
    "display_order": 16,
    "custom_preconds": "GIVEN that Author is creating a questionnaire\r\nAND Author is creating a date question",
    "custom_steps": null,
    "custom_expected": "THEN answer is formatted as...",
    "custom_steps_separated": null
  },
  {
    "id": 1217684,
    "title": "Author creates yes/no question",
    "section_id": 146537,
    "template_id": 1,
    "type_id": 4,
    "priority_id": 6,
    "milestone_id": null,
    "refs": "PROSPECT-32, PROSPECT-67",
    "created_by": 108,
    "created_on": 1517449460,
    "updated_by": 108,
    "updated_on": 1517450239,
    "estimate": null,
    "estimate_forecast": null,
    "suite_id": 20319,
    "display_order": 17,
    "custom_preconds": "GIVEN that Author is creating a questionnaire\r\nAND Author is creating a yes/no question",
    "custom_steps": null,
    "custom_expected": null,
    "custom_steps_separated": null
  },
  {
    "id": 1217685,
    "title": "Author creates multiple-choice question",
    "section_id": 146537,
    "template_id": 1,
    "type_id": 4,
    "priority_id": 6,
    "milestone_id": null,
    "refs": "PROSPECT-32, PROSPECT-68",
    "created_by": 108,
    "created_on": 1517449471,
    "updated_by": 108,
    "updated_on": 1517450256,
    "estimate": null,
    "estimate_forecast": null,
    "suite_id": 20319,
    "display_order": 18,
    "custom_preconds": "GIVEN that Author is creating a questionnaire\r\nAND Author is creating a multiple-choice question",
    "custom_steps": null,
    "custom_expected": "THEN question is formed with checkboxes.",
    "custom_steps_separated": null
  },
  {
    "id": 1217686,
    "title": "Author creates text box question",
    "section_id": 146537,
    "template_id": 1,
    "type_id": 4,
    "priority_id": 6,
    "milestone_id": null,
    "refs": "PROSPECT-32, PROSPECT-69",
    "created_by": 108,
    "created_on": 1517449479,
    "updated_by": 108,
    "updated_on": 1517450265,
    "estimate": null,
    "estimate_forecast": null,
    "suite_id": 20319,
    "display_order": 19,
    "custom_preconds": "GIVEN that Author is creating a questionnaire\r\nAND Author is creating a text box question",
    "custom_steps": null,
    "custom_expected": null,
    "custom_steps_separated": null
  },
  {
    "id": 1217687,
    "title": "Author creates stepper question",
    "section_id": 146537,
    "template_id": 1,
    "type_id": 4,
    "priority_id": 6,
    "milestone_id": null,
    "refs": "PROSPECT-32, PROSPECT-70",
    "created_by": 108,
    "created_on": 1517449484,
    "updated_by": 108,
    "updated_on": 1517450275,
    "estimate": null,
    "estimate_forecast": null,
    "suite_id": 20319,
    "display_order": 20,
    "custom_preconds": "GIVEN that Author is creating a questionnaire\r\nAND Author is creating a stepper question",
    "custom_steps": null,
    "custom_expected": "THEN question has a minus sign to the left of the answer\r\nAND question has a plus sign to the right of the answer\r\nAND answer is an integer\r\nAND Author defines minimum value for answer\r\nAND Author defines maximum value for answer.",
    "custom_steps_separated": null
  },
  {
    "id": 1217688,
    "title": "Author creates percent question",
    "section_id": 146537,
    "template_id": 1,
    "type_id": 4,
    "priority_id": 6,
    "milestone_id": null,
    "refs": "PROSPECT-32, PROSPECT-47, PROSPECT-71",
    "created_by": 108,
    "created_on": 1517449491,
    "updated_by": 108,
    "updated_on": 1517450286,
    "estimate": null,
    "estimate_forecast": null,
    "suite_id": 20319,
    "display_order": 21,
    "custom_preconds": "GIVEN that Author is creating a questionnaire\r\nAND Author is creating a percent question",
    "custom_steps": null,
    "custom_expected": "THEN answer must be between zero and 100\r\nAND answer can go up to 3 digits after decimal point.",
    "custom_steps_separated": null
  },
  {
    "id": 1217689,
    "title": "Author creates number question",
    "section_id": 146537,
    "template_id": 1,
    "type_id": 4,
    "priority_id": 6,
    "milestone_id": null,
    "refs": "PROSPECT-32, PROSPECT-46, PROSPECT-72",
    "created_by": 108,
    "created_on": 1517449500,
    "updated_by": 108,
    "updated_on": 1517450295,
    "estimate": null,
    "estimate_forecast": null,
    "suite_id": 20319,
    "display_order": 22,
    "custom_preconds": "GIVEN that Author is creating a questionnaire\r\nAND Author is creating a number question",
    "custom_steps": null,
    "custom_expected": "THEN answer can go up to 3 digits after the decimal point.",
    "custom_steps_separated": null
  },
  {
    "id": 1217690,
    "title": "Author creates slider question",
    "section_id": 146537,
    "template_id": 1,
    "type_id": 4,
    "priority_id": 6,
    "milestone_id": null,
    "refs": "PROSPECT-32, PROSPECT-73",
    "created_by": 108,
    "created_on": 1517449507,
    "updated_by": 108,
    "updated_on": 1517450306,
    "estimate": null,
    "estimate_forecast": null,
    "suite_id": 20319,
    "display_order": 23,
    "custom_preconds": "GIVEN that Author is creating a questionnaire\r\nAND Author is creating a slider question",
    "custom_steps": null,
    "custom_expected": "THEN answer is an integer\r\nAND Author defines minimum value\r\nAND Author defines maximum value.",
    "custom_steps_separated": null
  },
  {
    "id": 1217691,
    "title": "Author creates drag and drop ranking question",
    "section_id": 146537,
    "template_id": 1,
    "type_id": 4,
    "priority_id": 6,
    "milestone_id": null,
    "refs": "PROSPECT-32, PROSPECT-74",
    "created_by": 108,
    "created_on": 1517449516,
    "updated_by": 108,
    "updated_on": 1517450317,
    "estimate": null,
    "estimate_forecast": null,
    "suite_id": 20319,
    "display_order": 24,
    "custom_preconds": "GIVEN that Author is creating a questionnaire\r\nAND Author is creating a drag and drop ranking question",
    "custom_steps": null,
    "custom_expected": null,
    "custom_steps_separated": null
  },
  {
    "id": 1217692,
    "title": "Author creates single-answer grid",
    "section_id": 146537,
    "template_id": 1,
    "type_id": 4,
    "priority_id": 6,
    "milestone_id": null,
    "refs": "PROSPECT-32, PROSPECT-75",
    "created_by": 108,
    "created_on": 1517449525,
    "updated_by": 108,
    "updated_on": 1517450330,
    "estimate": null,
    "estimate_forecast": null,
    "suite_id": 20319,
    "display_order": 25,
    "custom_preconds": "GIVEN that Author is creating a questionnaire\r\nAND Author is creating a single-answer grid question",
    "custom_steps": null,
    "custom_expected": "THEN only one answer is accepted per row.",
    "custom_steps_separated": null
  },
  {
    "id": 1217693,
    "title": "Author creates multiple-answer grid",
    "section_id": 146537,
    "template_id": 1,
    "type_id": 4,
    "priority_id": 6,
    "milestone_id": null,
    "refs": "PROSPECT-32, PROSPECT-76",
    "created_by": 108,
    "created_on": 1517449533,
    "updated_by": 108,
    "updated_on": 1517450343,
    "estimate": null,
    "estimate_forecast": null,
    "suite_id": 20319,
    "display_order": 26,
    "custom_preconds": "GIVEN that Author is creating a questionnaire\r\nAND Author is creating a multiple-answer grid question",
    "custom_steps": null,
    "custom_expected": null,
    "custom_steps_separated": null
  },
  {
    "id": 1217694,
    "title": "Author creates follow-up question",
    "section_id": 146537,
    "template_id": 1,
    "type_id": 4,
    "priority_id": 6,
    "milestone_id": null,
    "refs": "PROSPECT-32, PROSPECT-81",
    "created_by": 108,
    "created_on": 1517449557,
    "updated_by": 108,
    "updated_on": 1517450153,
    "estimate": null,
    "estimate_forecast": null,
    "suite_id": 20319,
    "display_order": 27,
    "custom_preconds": "GIVEN that Author is creating a questionnaire\r\nAND Author is creating a follow-up question",
    "custom_steps": null,
    "custom_expected": "THEN parent question is a single-answer question\r\nOR parent question is a yes/no question\r\nOR parent question is a multiple-choice question\r\nAND parent question cannot be any other type of question.",
    "custom_steps_separated": null
  },
  {
    "id": 1219657,
    "title": "Author moves follow-up question",
    "section_id": 146537,
    "template_id": 1,
    "type_id": 4,
    "priority_id": 6,
    "milestone_id": null,
    "refs": "PROSPECT-102",
    "created_by": 108,
    "created_on": 1518718940,
    "updated_by": 108,
    "updated_on": 1518719031,
    "estimate": null,
    "estimate_forecast": null,
    "suite_id": 20319,
    "display_order": 28,
    "custom_preconds": "GIVEN that Author is creating a questionnaire\r\nAND Author is adding multiple follow-up questions to one question",
    "custom_steps": "WHEN Author drags and drops a follow-up question to a different location in the list of follow-up questions",
    "custom_expected": "THEN the follow-up questions re-order as intended.",
    "custom_steps_separated": null
  },
  {
    "id": 1217803,
    "title": "Test responsiveness",
    "section_id": 146537,
    "template_id": 1,
    "type_id": 4,
    "priority_id": 6,
    "milestone_id": null,
    "refs": null,
    "created_by": 108,
    "created_on": 1517692002,
    "updated_by": 108,
    "updated_on": 1517692002,
    "estimate": null,
    "estimate_forecast": null,
    "suite_id": 20319,
    "display_order": 29,
    "custom_preconds": null,
    "custom_steps": null,
    "custom_expected": null,
    "custom_steps_separated": null
  },
  {
    "id": 1217639,
    "title": "Header - appearance",
    "section_id": 146527,
    "template_id": 1,
    "type_id": 4,
    "priority_id": 6,
    "milestone_id": null,
    "refs": "https://wiki.mlbam.com/pages/viewpage.action?spaceKey=ECT&title=Individual+Functional+Requirements",
    "created_by": 108,
    "created_on": 1517443686,
    "updated_by": 108,
    "updated_on": 1517689992,
    "estimate": null,
    "estimate_forecast": null,
    "suite_id": 20319,
    "display_order": 1,
    "custom_preconds": "GIVEN that Scout is on the Draft Prospects website\r\nAND header has appeared",
    "custom_steps": null,
    "custom_expected": "THEN header has 2 elements: Draft Prospects logo, nav\r\nAND the nav has 5 options: Prospects, Surveys, Messages, Support, User Name\r\nAND the Surveys and User Name options have down-facing carats\r\nAND User Name is formatted: F. Last\r\nAND a dark blue rule appears above the nav option that is the current page.",
    "custom_steps_separated": null
  },
  {
    "id": 1217640,
    "title": "Header nav - hover",
    "section_id": 146527,
    "template_id": 1,
    "type_id": 4,
    "priority_id": 6,
    "milestone_id": null,
    "refs": "https://wiki.mlbam.com/pages/viewpage.action?spaceKey=ECT&title=Individual+Functional+Requirements",
    "created_by": 108,
    "created_on": 1517443995,
    "updated_by": 108,
    "updated_on": 1517444165,
    "estimate": null,
    "estimate_forecast": null,
    "suite_id": 20319,
    "display_order": 3,
    "custom_preconds": "GIVEN that Scout is on the Draft Prospects site\r\nAND header nav has appeared\r\nAND the blue rule has appeared above the nav option that is the current page",
    "custom_steps": "WHEN user hovers cursor over another option in the nav",
    "custom_expected": "THEN a second blue rule appears over that option.",
    "custom_steps_separated": null
  },
  {
    "id": 1217641,
    "title": "Header nav - hover over dropdown",
    "section_id": 146527,
    "template_id": 1,
    "type_id": 4,
    "priority_id": 6,
    "milestone_id": null,
    "refs": null,
    "created_by": 108,
    "created_on": 1517444012,
    "updated_by": 108,
    "updated_on": 1517444243,
    "estimate": null,
    "estimate_forecast": null,
    "suite_id": 20319,
    "display_order": 4,
    "custom_preconds": "GIVEN that Scout is on the Draft Prospects site\r\nAND header nav has appeared",
    "custom_steps": "WHEN Scout hovers cursor over a nav option with a down-facing carat",
    "custom_expected": "THEN that option's dropdown menu appears.",
    "custom_steps_separated": null
  },
  {
    "id": 1217804,
    "title": "Test responsiveness",
    "section_id": 146527,
    "template_id": 1,
    "type_id": 4,
    "priority_id": 6,
    "milestone_id": null,
    "refs": null,
    "created_by": 108,
    "created_on": 1517692019,
    "updated_by": 108,
    "updated_on": 1517692019,
    "estimate": null,
    "estimate_forecast": null,
    "suite_id": 20319,
    "display_order": 5,
    "custom_preconds": null,
    "custom_steps": null,
    "custom_expected": null,
    "custom_steps_separated": null
  },
  {
    "id": 1217805,
    "title": "Test on tablet",
    "section_id": 146527,
    "template_id": 1,
    "type_id": 4,
    "priority_id": 6,
    "milestone_id": null,
    "refs": null,
    "created_by": 108,
    "created_on": 1517692019,
    "updated_by": 108,
    "updated_on": 1517692019,
    "estimate": null,
    "estimate_forecast": null,
    "suite_id": 20319,
    "display_order": 6,
    "custom_preconds": null,
    "custom_steps": null,
    "custom_expected": null,
    "custom_steps_separated": null
  },
  {
    "id": 1217806,
    "title": "Test on mobile",
    "section_id": 146527,
    "template_id": 1,
    "type_id": 4,
    "priority_id": 6,
    "milestone_id": null,
    "refs": null,
    "created_by": 108,
    "created_on": 1517692019,
    "updated_by": 108,
    "updated_on": 1517692019,
    "estimate": null,
    "estimate_forecast": null,
    "suite_id": 20319,
    "display_order": 7,
    "custom_preconds": null,
    "custom_steps": null,
    "custom_expected": null,
    "custom_steps_separated": null
  },
  {
    "id": 1217742,
    "title": "Club cannot see another Club's invited prospects",
    "section_id": 146528,
    "template_id": 1,
    "type_id": 4,
    "priority_id": 4,
    "milestone_id": null,
    "refs": null,
    "created_by": 108,
    "created_on": 1517687920,
    "updated_by": 108,
    "updated_on": 1517688024,
    "estimate": null,
    "estimate_forecast": null,
    "suite_id": 20319,
    "display_order": 1,
    "custom_preconds": "GIVEN that user is a member of a Club\r\nAND user is on the Prospects page",
    "custom_steps": null,
    "custom_expected": "THEN user cannot see any prospects that were invited by another Club.",
    "custom_steps_separated": null
  },
  {
    "id": 1217743,
    "title": "Club can see Central Office invited prospects",
    "section_id": 146528,
    "template_id": 1,
    "type_id": 4,
    "priority_id": 4,
    "milestone_id": null,
    "refs": null,
    "created_by": 108,
    "created_on": 1517687930,
    "updated_by": 108,
    "updated_on": 1517688024,
    "estimate": null,
    "estimate_forecast": null,
    "suite_id": 20319,
    "display_order": 2,
    "custom_preconds": "GIVEN that user is a member of a Club\r\nAND user is on the Prospects page",
    "custom_steps": null,
    "custom_expected": "THEN user can see all prospects who were invited by the BOC Central Office.",
    "custom_steps_separated": null
  },
  {
    "id": 1217752,
    "title": "Prospects Page - Header - appearance",
    "section_id": 146528,
    "template_id": 1,
    "type_id": 4,
    "priority_id": 6,
    "milestone_id": null,
    "refs": "PROSPECT-112, https://wiki.mlbam.com/pages/viewpage.action?spaceKey=ECT&title=Individual+Functional+Requirements",
    "created_by": 108,
    "created_on": 1517689951,
    "updated_by": 108,
    "updated_on": 1519320165,
    "estimate": null,
    "estimate_forecast": null,
    "suite_id": 20319,
    "display_order": 3,
    "custom_preconds": "GIVEN that Scout is on the Draft Prospects website\r\nAND header has appeared",
    "custom_steps": null,
    "custom_expected": "THEN 2 elements have been added to the header: search box, new invite button\r\nAND inside the search box is a magnifying glass icon and the prompt: Search Roster Name\r\nAND the new invite button is a white + icon on a dark blue circle\r\n",
    "custom_steps_separated": null
  },
  {
    "id": 1217753,
    "title": "Prospects page - search function",
    "section_id": 146528,
    "template_id": 1,
    "type_id": 4,
    "priority_id": 6,
    "milestone_id": null,
    "refs": "PROSPECT-112",
    "created_by": 108,
    "created_on": 1517690070,
    "updated_by": 108,
    "updated_on": 1519320142,
    "estimate": null,
    "estimate_forecast": null,
    "suite_id": 20319,
    "display_order": 4,
    "custom_preconds": "GIVEN that Scout is on the Prospects page\r\nAND Scout has clicked or tapped inside the Search field",
    "custom_steps": "WHEN Scout starts typing in the Search field\r\nAND Scout types at least 2 letters\r\n",
    "custom_expected": "THEN Prospects chart produces results\r\nAND the results include only names that have the typed sequence of letters\r\nAND a close X link appears inside the Search field at the far right of the field.",
    "custom_steps_separated": null
  },
  {
    "id": 1217650,
    "title": "Prospects page - search produces no results",
    "section_id": 146528,
    "template_id": 1,
    "type_id": 4,
    "priority_id": 6,
    "milestone_id": null,
    "refs": "PROSPECT-40",
    "created_by": 108,
    "created_on": 1517445421,
    "updated_by": 108,
    "updated_on": 1517689891,
    "estimate": null,
    "estimate_forecast": null,
    "suite_id": 20319,
    "display_order": 5,
    "custom_preconds": null,
    "custom_steps": null,
    "custom_expected": null,
    "custom_steps_separated": null
  },
  {
    "id": 1217754,
    "title": "Prospects page - cancel search",
    "section_id": 146528,
    "template_id": 1,
    "type_id": 4,
    "priority_id": 7,
    "milestone_id": null,
    "refs": null,
    "created_by": 108,
    "created_on": 1517690246,
    "updated_by": 108,
    "updated_on": 1517690467,
    "estimate": null,
    "estimate_forecast": null,
    "suite_id": 20319,
    "display_order": 6,
    "custom_preconds": "GIVEN that Scout has searched for a Prospect\r\nAND X close link has appeared inside the Search field",
    "custom_steps": "WHEN Scout clicks or taps on the X close link inside the Search field",
    "custom_expected": "THEN typed characters disappear from the Search field\r\nAND the chart changes to show all Prospects.",
    "custom_steps_separated": null
  },
  {
    "id": 1217642,
    "title": "Prospects page - filters",
    "section_id": 146528,
    "template_id": 1,
    "type_id": 4,
    "priority_id": 6,
    "milestone_id": null,
    "refs": "https://wiki.mlbam.com/pages/viewpage.action?spaceKey=ECT&title=Individual+Functional+Requirements",
    "created_by": 108,
    "created_on": 1517444260,
    "updated_by": 108,
    "updated_on": 1517444425,
    "estimate": null,
    "estimate_forecast": null,
    "suite_id": 20319,
    "display_order": 7,
    "custom_preconds": "GIVEN that Scout is on the Prospects page\r\n",
    "custom_steps": null,
    "custom_expected": "THEN below the Draft Prospects logo is a row of filter buttons\r\nAND the filter buttons are labeled: Draft Year, Invitations, Survey Response, Location, Position, More Filters.",
    "custom_steps_separated": null
  },
  {
    "id": 1217643,
    "title": "Prospects page - pagination",
    "section_id": 146528,
    "template_id": 1,
    "type_id": 4,
    "priority_id": 6,
    "milestone_id": null,
    "refs": "https://wiki.mlbam.com/pages/viewpage.action?spaceKey=ECT&title=Individual+Functional+Requirements",
    "created_by": 108,
    "created_on": 1517444269,
    "updated_by": 108,
    "updated_on": 1517444770,
    "estimate": null,
    "estimate_forecast": null,
    "suite_id": 20319,
    "display_order": 8,
    "custom_preconds": "GIVEN that Scout is on the Prospects page",
    "custom_steps": null,
    "custom_expected": "THEN below the header nav are 3 pagination elements: pages, carat, Prospect count\r\nAND the element on the left is 1, 2, 3, ellipses, x\r\nAND x is the total number of pages\r\nAND the numbers and ellipses are dark blue\r\nAND the number of the current page is white with a dark blue circle behind it\r\nAND next to x is a right-facing carat\r\nAND the carat is circled with a dark blue border\r\nAND centered below the pagination and carat is the Prospect count\r\nAND the count is formatted: 1 - y of z+ Prospects\r\nAND y is the total of Prospects visible on this screen\r\nAND z is the total Prospects rounded to the nearest hundred.",
    "custom_steps_separated": null
  },
  {
    "id": 1217644,
    "title": "Prospects page - chart column headers",
    "section_id": 146528,
    "template_id": 1,
    "type_id": 4,
    "priority_id": 6,
    "milestone_id": null,
    "refs": "https://wiki.mlbam.com/pages/viewpage.action?spaceKey=ECT&title=Individual+Functional+Requirements",
    "created_by": 108,
    "created_on": 1517444278,
    "updated_by": 108,
    "updated_on": 1519320192,
    "estimate": null,
    "estimate_forecast": null,
    "suite_id": 20319,
    "display_order": 9,
    "custom_preconds": "GIVEN that Scout is on the Prospects page\r\nAND Prospects chart has appeared",
    "custom_steps": null,
    "custom_expected": "THEN the chart column headers are: \r\nRoster Name\r\nSort A-Z\r\nSchool Name\r\nSchool State\r\nInvite Date\r\nSign Up Date\r\nInvited By\r\nUnfinished Item(s)\r\nAction dropdown\r\nSelect All checkbox",
    "custom_steps_separated": null
  },
  {
    "id": 1220031,
    "title": "Prospects page - BOC invited prospects appear",
    "section_id": 146528,
    "template_id": 1,
    "type_id": 4,
    "priority_id": 6,
    "milestone_id": null,
    "refs": "PROSPECT-112",
    "created_by": 108,
    "created_on": 1519320236,
    "updated_by": 108,
    "updated_on": 1519320540,
    "estimate": null,
    "estimate_forecast": null,
    "suite_id": 20319,
    "display_order": 10,
    "custom_preconds": "GIVEN that Scout is on the Club's Prospects page\r\nAND Prospects chart has appeared",
    "custom_steps": "WHEN the Scouting Bureau has invited a Prospect to sign up on DP",
    "custom_expected": "THEN that Prospect appears in the Prospects chart whether or not he has signed up yet\r\nAND the Invited By column for that Prospect displays \"Scouting Bureau.\"",
    "custom_steps_separated": null
  },
  {
    "id": 1217645,
    "title": "Prospects page - chart centering",
    "section_id": 146528,
    "template_id": 1,
    "type_id": 4,
    "priority_id": 6,
    "milestone_id": null,
    "refs": "https://wiki.mlbam.com/pages/viewpage.action?spaceKey=ECT&title=Individual+Functional+Requirements",
    "created_by": 108,
    "created_on": 1517444300,
    "updated_by": 108,
    "updated_on": 1517444963,
    "estimate": null,
    "estimate_forecast": null,
    "suite_id": 20319,
    "display_order": 11,
    "custom_preconds": "GIVEN that Scout is on the Prospects page\r\nAND Prospects chart has appeared",
    "custom_steps": null,
    "custom_expected": "THEN all entries under Name are left-aligned\r\nAND all other entries are horizontally centered in their columns.",
    "custom_steps_separated": null
  },
  {
    "id": 1217646,
    "title": "Prospects page - linked names",
    "section_id": 146528,
    "template_id": 1,
    "type_id": 4,
    "priority_id": 6,
    "milestone_id": null,
    "refs": "https://wiki.mlbam.com/pages/viewpage.action?spaceKey=ECT&title=Individual+Functional+Requirements",
    "created_by": 108,
    "created_on": 1517444308,
    "updated_by": 108,
    "updated_on": 1517445032,
    "estimate": null,
    "estimate_forecast": null,
    "suite_id": 20319,
    "display_order": 12,
    "custom_preconds": "GIVEN that Scout is on the Prospects page\r\nAND Prospects chart has appeared",
    "custom_steps": null,
    "custom_expected": "THEN the name of any Prospect who has signed up to DP is blue and underlined\r\nAND the name is linked to the Prospect's individual page.",
    "custom_steps_separated": null
  },
  {
    "id": 1217647,
    "title": "Prospects page - Sign Up Date warning icon",
    "section_id": 146528,
    "template_id": 1,
    "type_id": 4,
    "priority_id": 6,
    "milestone_id": null,
    "refs": "https://wiki.mlbam.com/pages/viewpage.action?spaceKey=ECT&title=Individual+Functional+Requirements",
    "created_by": 108,
    "created_on": 1517444324,
    "updated_by": 108,
    "updated_on": 1517445135,
    "estimate": null,
    "estimate_forecast": null,
    "suite_id": 20319,
    "display_order": 13,
    "custom_preconds": "GIVEN that Scout is on the Prospects page\r\nAND Prospects chart has appeared",
    "custom_steps": "WHEN a Prospect's first invite is over 30 days old ",
    "custom_expected": "THEN a warning icon appears in the Prospect's Sign Up Date field\r\nAND the warning icon is a red exclamation point inside a red-bordered triangle.",
    "custom_steps_separated": null
  },
  {
    "id": 1217651,
    "title": "Prospects page - restricted view",
    "section_id": 146528,
    "template_id": 1,
    "type_id": 4,
    "priority_id": 6,
    "milestone_id": null,
    "refs": null,
    "created_by": 108,
    "created_on": 1517445488,
    "updated_by": 108,
    "updated_on": 1517446484,
    "estimate": null,
    "estimate_forecast": null,
    "suite_id": 20319,
    "display_order": 14,
    "custom_preconds": "GIVEN Scout is on Prospects page",
    "custom_steps": null,
    "custom_expected": "THEN Scout can see Prospects invited by own Club\r\nAND Scout can see Prospects invited by Central Office\r\nAND Scout cannot see Prospects invited by other Clubs.",
    "custom_steps_separated": null
  },
  {
    "id": 1217653,
    "title": "QUESTION: Scout views Top 50/300?",
    "section_id": 146528,
    "template_id": 1,
    "type_id": 4,
    "priority_id": 6,
    "milestone_id": null,
    "refs": null,
    "created_by": 108,
    "created_on": 1517446078,
    "updated_by": 108,
    "updated_on": 1517446078,
    "estimate": null,
    "estimate_forecast": null,
    "suite_id": 20319,
    "display_order": 15,
    "custom_preconds": null,
    "custom_steps": null,
    "custom_expected": null,
    "custom_steps_separated": null
  },
  {
    "id": 1217807,
    "title": "Test responsiveness",
    "section_id": 146528,
    "template_id": 1,
    "type_id": 4,
    "priority_id": 6,
    "milestone_id": null,
    "refs": null,
    "created_by": 108,
    "created_on": 1517692024,
    "updated_by": 108,
    "updated_on": 1517692024,
    "estimate": null,
    "estimate_forecast": null,
    "suite_id": 20319,
    "display_order": 16,
    "custom_preconds": null,
    "custom_steps": null,
    "custom_expected": null,
    "custom_steps_separated": null
  },
  {
    "id": 1217808,
    "title": "Test on tablet",
    "section_id": 146528,
    "template_id": 1,
    "type_id": 4,
    "priority_id": 6,
    "milestone_id": null,
    "refs": null,
    "created_by": 108,
    "created_on": 1517692024,
    "updated_by": 108,
    "updated_on": 1517692024,
    "estimate": null,
    "estimate_forecast": null,
    "suite_id": 20319,
    "display_order": 17,
    "custom_preconds": null,
    "custom_steps": null,
    "custom_expected": null,
    "custom_steps_separated": null
  },
  {
    "id": 1217809,
    "title": "Test on mobile",
    "section_id": 146528,
    "template_id": 1,
    "type_id": 4,
    "priority_id": 6,
    "milestone_id": null,
    "refs": null,
    "created_by": 108,
    "created_on": 1517692024,
    "updated_by": 108,
    "updated_on": 1517692024,
    "estimate": null,
    "estimate_forecast": null,
    "suite_id": 20319,
    "display_order": 18,
    "custom_preconds": null,
    "custom_steps": null,
    "custom_expected": null,
    "custom_steps_separated": null
  },
  {
    "id": 1220032,
    "title": "Prospects page - sort by name",
    "section_id": 146528,
    "template_id": 1,
    "type_id": 4,
    "priority_id": 6,
    "milestone_id": null,
    "refs": "PROSPECT-112",
    "created_by": 108,
    "created_on": 1519320554,
    "updated_by": 108,
    "updated_on": 1519320599,
    "estimate": null,
    "estimate_forecast": null,
    "suite_id": 20319,
    "display_order": 19,
    "custom_preconds": "GIVEN that Scout is on the Prospects page\r\nAND Prospects chart has appeared",
    "custom_steps": "WHEN Scout sorts by name",
    "custom_expected": "THEN the Prospects are sorted by their last names.",
    "custom_steps_separated": null
  },
  {
    "id": 1217652,
    "title": "QUESTION: Scout sees notifications?",
    "section_id": 146530,
    "template_id": 1,
    "type_id": 4,
    "priority_id": 6,
    "milestone_id": null,
    "refs": null,
    "created_by": 108,
    "created_on": 1517445854,
    "updated_by": 108,
    "updated_on": 1517445858,
    "estimate": null,
    "estimate_forecast": null,
    "suite_id": 20319,
    "display_order": 1,
    "custom_preconds": null,
    "custom_steps": null,
    "custom_expected": null,
    "custom_steps_separated": null
  },
  {
    "id": 1217648,
    "title": "Scout can download",
    "section_id": 146530,
    "template_id": 1,
    "type_id": 4,
    "priority_id": 6,
    "milestone_id": null,
    "refs": "PROSPECT-37",
    "created_by": 108,
    "created_on": 1517445179,
    "updated_by": 108,
    "updated_on": 1517445321,
    "estimate": null,
    "estimate_forecast": null,
    "suite_id": 20319,
    "display_order": 2,
    "custom_preconds": "When a download option exists, it works.",
    "custom_steps": null,
    "custom_expected": null,
    "custom_steps_separated": null
  },
  {
    "id": 1217649,
    "title": "Scout can view all relevant screens",
    "section_id": 146530,
    "template_id": 1,
    "type_id": 4,
    "priority_id": 6,
    "milestone_id": null,
    "refs": "PROSPECT-36",
    "created_by": 108,
    "created_on": 1517445336,
    "updated_by": 108,
    "updated_on": 1517445356,
    "estimate": null,
    "estimate_forecast": null,
    "suite_id": 20319,
    "display_order": 3,
    "custom_preconds": null,
    "custom_steps": null,
    "custom_expected": null,
    "custom_steps_separated": null
  },
  {
    "id": 1217657,
    "title": "Scout views a Prospect's questionnaires",
    "section_id": 146533,
    "template_id": 1,
    "type_id": 4,
    "priority_id": 6,
    "milestone_id": null,
    "refs": null,
    "created_by": 108,
    "created_on": 1517446738,
    "updated_by": 108,
    "updated_on": 1517446738,
    "estimate": null,
    "estimate_forecast": null,
    "suite_id": 20319,
    "display_order": 1,
    "custom_preconds": null,
    "custom_steps": null,
    "custom_expected": null,
    "custom_steps_separated": null
  },
  {
    "id": 1217658,
    "title": "Scout views a report of multiple questionnaires",
    "section_id": 146533,
    "template_id": 1,
    "type_id": 4,
    "priority_id": 6,
    "milestone_id": null,
    "refs": null,
    "created_by": 108,
    "created_on": 1517446761,
    "updated_by": 108,
    "updated_on": 1517446820,
    "estimate": null,
    "estimate_forecast": null,
    "suite_id": 20319,
    "display_order": 3,
    "custom_preconds": null,
    "custom_steps": null,
    "custom_expected": null,
    "custom_steps_separated": null
  },
  {
    "id": 1217659,
    "title": "Report is searchable with CTRL-F",
    "section_id": 146533,
    "template_id": 1,
    "type_id": 4,
    "priority_id": 6,
    "milestone_id": null,
    "refs": null,
    "created_by": 108,
    "created_on": 1517446790,
    "updated_by": 108,
    "updated_on": 1517446790,
    "estimate": null,
    "estimate_forecast": null,
    "suite_id": 20319,
    "display_order": 4,
    "custom_preconds": null,
    "custom_steps": null,
    "custom_expected": null,
    "custom_steps_separated": null
  },
  {
    "id": 1217660,
    "title": "Scout downloads report as raw data",
    "section_id": 146533,
    "template_id": 1,
    "type_id": 4,
    "priority_id": 6,
    "milestone_id": null,
    "refs": null,
    "created_by": 108,
    "created_on": 1517446836,
    "updated_by": 108,
    "updated_on": 1517446836,
    "estimate": null,
    "estimate_forecast": null,
    "suite_id": 20319,
    "display_order": 5,
    "custom_preconds": null,
    "custom_steps": null,
    "custom_expected": null,
    "custom_steps_separated": null
  },
  {
    "id": 1217661,
    "title": "QUESTION: Scout downloads report in .pdf form?",
    "section_id": 146533,
    "template_id": 1,
    "type_id": 4,
    "priority_id": 6,
    "milestone_id": null,
    "refs": "PROSPECT-22",
    "created_by": 108,
    "created_on": 1517446859,
    "updated_by": 108,
    "updated_on": 1517446904,
    "estimate": null,
    "estimate_forecast": null,
    "suite_id": 20319,
    "display_order": 6,
    "custom_preconds": null,
    "custom_steps": null,
    "custom_expected": ".pdf form could look like a paper survey?",
    "custom_steps_separated": null
  },
  {
    "id": 1217813,
    "title": "Test responsiveness",
    "section_id": 146533,
    "template_id": 1,
    "type_id": 4,
    "priority_id": 6,
    "milestone_id": null,
    "refs": null,
    "created_by": 108,
    "created_on": 1517692045,
    "updated_by": 108,
    "updated_on": 1517692045,
    "estimate": null,
    "estimate_forecast": null,
    "suite_id": 20319,
    "display_order": 7,
    "custom_preconds": null,
    "custom_steps": null,
    "custom_expected": null,
    "custom_steps_separated": null
  },
  {
    "id": 1217814,
    "title": "Test on tablet",
    "section_id": 146533,
    "template_id": 1,
    "type_id": 4,
    "priority_id": 6,
    "milestone_id": null,
    "refs": null,
    "created_by": 108,
    "created_on": 1517692045,
    "updated_by": 108,
    "updated_on": 1517692045,
    "estimate": null,
    "estimate_forecast": null,
    "suite_id": 20319,
    "display_order": 8,
    "custom_preconds": null,
    "custom_steps": null,
    "custom_expected": null,
    "custom_steps_separated": null
  },
  {
    "id": 1217815,
    "title": "Test on mobile",
    "section_id": 146533,
    "template_id": 1,
    "type_id": 4,
    "priority_id": 6,
    "milestone_id": null,
    "refs": null,
    "created_by": 108,
    "created_on": 1517692045,
    "updated_by": 108,
    "updated_on": 1517692045,
    "estimate": null,
    "estimate_forecast": null,
    "suite_id": 20319,
    "display_order": 9,
    "custom_preconds": null,
    "custom_steps": null,
    "custom_expected": null,
    "custom_steps_separated": null
  }
]